[
  {
    "status": "active",
    "rating": "3.61",
    "campaign": {
      "id": 17314,
      "name": "Depositphotos [CPS] WW",
      "site_url": "https://depositphotos.com/"
    },
    "description": "",
    "short_name": "15% Discount for On Demand Downloads and subscription purchase",
    "exclusive": false,
    "date_end": null,
    "date_start": "2024-06-12T15:28:55",
    "id": 766893,
    "regions": [
      "AD",
      "AE",
      "AG",
      "AI",
      "AL",
      "AM",
      "AO",
      "AQ",
      "AR",
      "AS",
      "AT",
      "AU",
      "AW",
      "AX",
      "AZ",
      "BA",
      "BB",
      "BD",
      "BE",
      "BF",
      "BG",
      "BH",
      "BI",
      "BJ",
      "BL",
      "BM",
      "BN",
      "BO",
      "BQ",
      "BR",
      "BS",
      "BT",
      "BV",
      "BW",
      "BZ",
      "CA",
      "CC",
      "CD",
      "CF",
      "CG",
      "CH",
      "CI",
      "CK",
      "CL",
      "CM",
      "CN",
      "CO",
      "CR",
      "CU",
      "CV",
      "CW",
      "CX",
      "CY",
      "CZ",
      "DE",
      "DJ",
      "DK",
      "DM",
      "DO",
      "DZ",
      "EC",
      "EE",
      "EG",
      "EH",
      "ER",
      "ES",
      "ET",
      "FI",
      "FJ",
      "FK",
      "FM",
      "FO",
      "FR",
      "GA",
      "GB",
      "GD",
      "GE",
      "GF",
      "GG",
      "GH",
      "GI",
      "GL",
      "GM",
      "GN",
      "GP",
      "GQ",
      "GR",
      "GS",
      "GT",
      "GU",
      "GW",
      "GY",
      "HK",
      "HM",
      "HN",
      "HR",
      "HT",
      "HU",
      "ID",
      "IE",
      "IL",
      "IM",
      "IN",
      "IO",
      "IQ",
      "IR",
      "IS",
      "IT",
      "JE",
      "JM",
      "JO",
      "JP",
      "KE",
      "KG",
      "KH",
      "KI",
      "KM",
      "KN",
      "KP",
      "KR",
      "KW",
      "KY",
      "KZ",
      "LA",
      "LB",
      "LC",
      "LI",
      "LK",
      "LR",
      "LS",
      "LT",
      "LU",
      "LV",
      "LY",
      "MA",
      "MC",
      "MD",
      "ME",
      "MF",
      "MG",
      "MH",
      "MK",
      "ML",
      "MM",
      "MN",
      "MO",
      "MP",
      "MQ",
      "MR",
      "MS",
      "MT",
      "MU",
      "MV",
      "MW",
      "MX",
      "MY",
      "MZ",
      "NA",
      "NC",
      "NE",
      "NF",
      "NG",
      "NI",
      "NL",
      "NO",
      "NP",
      "NR",
      "NU",
      "NZ",
      "OM",
      "PA",
      "PE",
      "PF",
      "PG",
      "PH",
      "PK",
      "PL",
      "PM",
      "PN",
      "PR",
      "PS",
      "PT",
      "PW",
      "PY",
      "QA",
      "RE",
      "RO",
      "RS",
      "RW",
      "SA",
      "SB",
      "SC",
      "SD",
      "SE",
      "SG",
      "SH",
      "SI",
      "SJ",
      "SK",
      "SL",
      "SM",
      "SN",
      "SO",
      "SR",
      "SS",
      "ST",
      "SV",
      "SX",
      "SY",
      "SZ",
      "TC",
      "TD",
      "TF",
      "TG",
      "TH",
      "TJ",
      "TK",
      "TL",
      "TM",
      "TN",
      "TO",
      "TR",
      "TT",
      "TV",
      "TW",
      "TZ",
      "UA",
      "UG",
      "UM",
      "US",
      "UY",
      "UZ",
      "VA",
      "VC",
      "VE",
      "VG",
      "VI",
      "VN",
      "VU",
      "WF",
      "WS",
      "YE",
      "YT",
      "ZA",
      "ZM",
      "ZW"
    ],
    "discount": "15%",
    "types": [
      {
        "id": 2,
        "name": "Order discount"
      }
    ],
    "image": "http://cdn.admitad.com/campaign/images/2025/10/27/17314-c3f358b37b3c9295.svg",
    "species": "promocode",
    "categories": [
      {
        "id": 21,
        "name": "Services"
      }
    ],
    "name": "15% Discount for On Demand Downloads and subscription purchase",
    "language": "en",
    "is_unique": false,
    "is_personal": false,
    "is_tracking_promo_code": false,
    "customer_type": null,
    "has_affiliate_link": true,
    "promocode": "152024",
    "frameset_link": "",
    "goto_link": "https://dhwnh.com/g/ph3kvykklk5af0702a276f61936a04/?i=3"
  },
  {
    "status": "active",
    "rating": "0.00",
    "campaign": {
      "id": 17314,
      "name": "Depositphotos [CPS] WW",
      "site_url": "https://depositphotos.com/"
    },
    "description": "",
    "short_name": "30% off on subscription",
    "exclusive": false,
    "date_end": null,
    "date_start": "2023-07-19T00:00:00",
    "id": 559334,
    "regions": [
      "AD",
      "AE",
      "AG",
      "AI",
      "AL",
      "AM",
      "AO",
      "AQ",
      "AR",
      "AS",
      "AT",
      "AU",
      "AW",
      "AX",
      "AZ",
      "BA",
      "BB",
      "BD",
      "BE",
      "BF",
      "BG",
      "BH",
      "BI",
      "BJ",
      "BL",
      "BM",
      "BN",
      "BO",
      "BQ",
      "BR",
      "BS",
      "BT",
      "BV",
      "BW",
      "BZ",
      "CA",
      "CC",
      "CD",
      "CF",
      "CG",
      "CH",
      "CI",
      "CK",
      "CL",
      "CM",
      "CN",
      "CO",
      "CR",
      "CU",
      "CV",
      "CW",
      "CX",
      "CY",
      "CZ",
      "DE",
      "DJ",
      "DK",
      "DM",
      "DO",
      "DZ",
      "EC",
      "EE",
      "EG",
      "EH",
      "ER",
      "ES",
      "ET",
      "FI",
      "FJ",
      "FK",
      "FM",
      "FO",
      "FR",
      "GA",
      "GB",
      "GD",
      "GE",
      "GF",
      "GG",
      "GH",
      "GI",
      "GL",
      "GM",
      "GN",
      "GP",
      "GQ",
      "GR",
      "GS",
      "GT",
      "GU",
      "GW",
      "GY",
      "HK",
      "HM",
      "HN",
      "HR",
      "HT",
      "HU",
      "ID",
      "IE",
      "IL",
      "IM",
      "IN",
      "IO",
      "IQ",
      "IR",
      "IS",
      "IT",
      "JE",
      "JM",
      "JO",
      "JP",
      "KE",
      "KG",
      "KH",
      "KI",
      "KM",
      "KN",
      "KP",
      "KR",
      "KW",
      "KY",
      "KZ",
      "LA",
      "LB",
      "LC",
      "LI",
      "LK",
      "LR",
      "LS",
      "LT",
      "LU",
      "LV",
      "LY",
      "MA",
      "MC",
      "MD",
      "ME",
      "MF",
      "MG",
      "MH",
      "MK",
      "ML",
      "MM",
      "MN",
      "MO",
      "MP",
      "MQ",
      "MR",
      "MS",
      "MT",
      "MU",
      "MV",
      "MW",
      "MX",
      "MY",
      "MZ",
      "NA",
      "NC",
      "NE",
      "NF",
      "NG",
      "NI",
      "NL",
      "NO",
      "NP",
      "NR",
      "NU",
      "NZ",
      "OM",
      "PA",
      "PE",
      "PF",
      "PG",
      "PH",
      "PK",
      "PL",
      "PM",
      "PN",
      "PR",
      "PS",
      "PT",
      "PW",
      "PY",
      "QA",
      "RE",
      "RO",
      "RS",
      "RW",
      "SA",
      "SB",
      "SC",
      "SD",
      "SE",
      "SG",
      "SH",
      "SI",
      "SJ",
      "SK",
      "SL",
      "SM",
      "SN",
      "SO",
      "SR",
      "SS",
      "ST",
      "SV",
      "SX",
      "SY",
      "SZ",
      "TC",
      "TD",
      "TF",
      "TG",
      "TH",
      "TJ",
      "TK",
      "TL",
      "TM",
      "TN",
      "TO",
      "TR",
      "TT",
      "TV",
      "TW",
      "TZ",
      "UA",
      "UG",
      "UM",
      "US",
      "UY",
      "UZ",
      "VA",
      "VC",
      "VE",
      "VG",
      "VI",
      "VN",
      "VU",
      "WF",
      "WS",
      "YE",
      "YT",
      "ZA",
      "ZM",
      "ZW"
    ],
    "discount": "30%",
    "types": [
      {
        "id": 2,
        "name": "Order discount"
      }
    ],
    "image": "http://cdn.admitad.com/campaign/images/2025/10/27/17314-c3f358b37b3c9295.svg",
    "species": "action",
    "categories": [
      {
        "id": 21,
        "name": "Services"
      }
    ],
    "name": "30% off on subscription",
    "language": "en",
    "is_unique": false,
    "is_personal": false,
    "is_tracking_promo_code": false,
    "customer_type": null,
    "has_affiliate_link": true,
    "promocode": "NOT REQUIRED",
    "frameset_link": "",
    "goto_link": "https://dhwnh.com/g/txiywrpk7c5af0702a276f61936a04/?i=3"
  }
]