[
  {
    "status": "active",
    "rating": "0.00",
    "campaign": {
      "id": 20543,
      "name": "Redmagic WW",
      "site_url": "https://global.redmagic.gg/"
    },
    "description": "",
    "short_name": "$5 off on REDMAGIC Turbo Cooler",
    "exclusive": false,
    "date_end": null,
    "date_start": "2024-07-04T12:22:56",
    "id": 772727,
    "regions": [
      "AE",
      "AT",
      "AU",
      "BE",
      "BG",
      "BR",
      "CA",
      "CL",
      "CY",
      "CZ",
      "DE",
      "DK",
      "EE",
      "EG",
      "ES",
      "FI",
      "FR",
      "GB",
      "GR",
      "HK",
      "HR",
      "HU",
      "ID",
      "IE",
      "IL",
      "IT",
      "KW",
      "LT",
      "LU",
      "LV",
      "MT",
      "MX",
      "NL",
      "NZ",
      "PH",
      "PL",
      "PT",
      "PY",
      "RO",
      "SA",
      "SE",
      "SG",
      "SI",
      "SK",
      "US"
    ],
    "discount": "5 $",
    "types": [
      {
        "id": 2,
        "name": "Order discount"
      }
    ],
    "image": "http://cdn.admitad.com/campaign/images/2025/9/5/20543-75ebe1c2bc996c2b.svg",
    "species": "action",
    "categories": [
      {
        "id": 8,
        "name": "Computers & Electronics"
      }
    ],
    "name": "$5 off on REDMAGIC Turbo Cooler",
    "language": "en",
    "is_unique": false,
    "is_personal": false,
    "is_tracking_promo_code": false,
    "customer_type": null,
    "has_affiliate_link": true,
    "promocode": "NOT REQUIRED",
    "frameset_link": "https://yyczo.com/coupon/w8sz9nn85n5af0702a2756637026d8/",
    "goto_link": "https://yyczo.com/g/yr0dpf848a5af0702a2756637026d8/?i=3"
  },
  {
    "status": "active",
    "rating": "0.00",
    "campaign": {
      "id": 20543,
      "name": "Redmagic WW",
      "site_url": "https://global.redmagic.gg/"
    },
    "description": "",
    "short_name": "$40 on REDMAGIC Mechanical Keyboard",
    "exclusive": false,
    "date_end": null,
    "date_start": "2024-07-04T12:14:08",
    "id": 772726,
    "regions": [
      "AE",
      "AT",
      "AU",
      "BE",
      "BG",
      "BR",
      "CA",
      "CL",
      "CY",
      "CZ",
      "DE",
      "DK",
      "EE",
      "EG",
      "ES",
      "FI",
      "FR",
      "GB",
      "GR",
      "HK",
      "HR",
      "HU",
      "ID",
      "IE",
      "IL",
      "IT",
      "KW",
      "LT",
      "LU",
      "LV",
      "MT",
      "MX",
      "NL",
      "NZ",
      "PH",
      "PL",
      "PT",
      "PY",
      "RO",
      "SA",
      "SE",
      "SG",
      "SI",
      "SK",
      "US"
    ],
    "discount": "40 $",
    "types": [
      {
        "id": 2,
        "name": "Order discount"
      }
    ],
    "image": "http://cdn.admitad.com/campaign/images/2025/9/5/20543-75ebe1c2bc996c2b.svg",
    "species": "action",
    "categories": [
      {
        "id": 8,
        "name": "Computers & Electronics"
      }
    ],
    "name": "$40 on REDMAGIC Mechanical Keyboard",
    "language": "en",
    "is_unique": false,
    "is_personal": false,
    "is_tracking_promo_code": false,
    "customer_type": null,
    "has_affiliate_link": true,
    "promocode": "NOT REQUIRED",
    "frameset_link": "https://yyczo.com/coupon/th01vr3vv75af0702a2756637026d8/",
    "goto_link": "https://yyczo.com/g/epgiwzvfy85af0702a2756637026d8/?i=3"
  },
  {
    "status": "active",
    "rating": "0.00",
    "campaign": {
      "id": 20543,
      "name": "Redmagic WW",
      "site_url": "https://global.redmagic.gg/"
    },
    "description": "",
    "short_name": "$5 off on REDMAGIC 9 Pro with VC Cooler 5 Pro Bundle",
    "exclusive": false,
    "date_end": null,
    "date_start": "2024-05-29T15:03:25",
    "id": 762247,
    "regions": [
      "AE",
      "AT",
      "AU",
      "BE",
      "BG",
      "BR",
      "CA",
      "CL",
      "CY",
      "CZ",
      "DE",
      "DK",
      "EE",
      "EG",
      "ES",
      "FI",
      "FR",
      "GB",
      "GR",
      "HK",
      "HR",
      "HU",
      "ID",
      "IE",
      "IL",
      "IT",
      "KW",
      "LT",
      "LU",
      "LV",
      "MT",
      "MX",
      "NL",
      "NZ",
      "PH",
      "PL",
      "PT",
      "PY",
      "RO",
      "SA",
      "SE",
      "SG",
      "SI",
      "SK",
      "US"
    ],
    "discount": "5 $",
    "types": [
      {
        "id": 2,
        "name": "Order discount"
      }
    ],
    "image": "http://cdn.admitad.com/campaign/images/2025/9/5/20543-75ebe1c2bc996c2b.svg",
    "species": "action",
    "categories": [
      {
        "id": 8,
        "name": "Computers & Electronics"
      },
      {
        "id": 19,
        "name": "Games"
      }
    ],
    "name": "$5 off on REDMAGIC 9 Pro with VC Cooler 5 Pro Bundle",
    "language": "en",
    "is_unique": false,
    "is_personal": false,
    "is_tracking_promo_code": false,
    "customer_type": null,
    "has_affiliate_link": true,
    "promocode": "NOT REQUIRED",
    "frameset_link": "https://yyczo.com/coupon/v2q50fozex5af0702a2756637026d8/",
    "goto_link": "https://yyczo.com/g/kf8kbeinqg5af0702a2756637026d8/?i=3"
  },
  {
    "status": "active",
    "rating": "0.00",
    "campaign": {
      "id": 20543,
      "name": "Redmagic WW",
      "site_url": "https://global.redmagic.gg/"
    },
    "description": "",
    "short_name": "REDMAGIC 4K Gaming Monitor with a FREE mouse pad",
    "exclusive": false,
    "date_end": null,
    "date_start": "2024-05-29T14:58:47",
    "id": 762246,
    "regions": [
      "AE",
      "AT",
      "AU",
      "BE",
      "BG",
      "BR",
      "CA",
      "CL",
      "CY",
      "CZ",
      "DE",
      "DK",
      "EE",
      "EG",
      "ES",
      "FI",
      "FR",
      "GB",
      "GR",
      "HK",
      "HR",
      "HU",
      "ID",
      "IE",
      "IL",
      "IT",
      "KW",
      "LT",
      "LU",
      "LV",
      "MT",
      "MX",
      "NL",
      "NZ",
      "PH",
      "PL",
      "PT",
      "PY",
      "RO",
      "SA",
      "SE",
      "SG",
      "SI",
      "SK",
      "US"
    ],
    "discount": null,
    "types": [
      {
        "id": 3,
        "name": "Gift for an order"
      }
    ],
    "image": "http://cdn.admitad.com/campaign/images/2025/9/5/20543-75ebe1c2bc996c2b.svg",
    "species": "promocode",
    "categories": [
      {
        "id": 8,
        "name": "Computers & Electronics"
      },
      {
        "id": 19,
        "name": "Games"
      }
    ],
    "name": "REDMAGIC 4K Gaming Monitor with a FREE mouse pad",
    "language": "en",
    "is_unique": false,
    "is_personal": false,
    "is_tracking_promo_code": false,
    "customer_type": null,
    "has_affiliate_link": true,
    "promocode": "RMFMP",
    "frameset_link": "https://yyczo.com/coupon/2ie4ezu18e5af0702a2756637026d8/",
    "goto_link": "https://yyczo.com/g/du65wesc5q5af0702a2756637026d8/?i=3"
  },
  {
    "status": "active",
    "rating": "0.00",
    "campaign": {
      "id": 20543,
      "name": "Redmagic WW",
      "site_url": "https://global.redmagic.gg/"
    },
    "description": "",
    "short_name": "$10 off on REDMAGIC 9 Pro with Gamepad 1 Bundle",
    "exclusive": false,
    "date_end": null,
    "date_start": "2024-05-14T15:08:26",
    "id": 756495,
    "regions": [
      "AE",
      "AT",
      "AU",
      "BE",
      "BG",
      "BR",
      "CA",
      "CL",
      "CY",
      "CZ",
      "DE",
      "DK",
      "EE",
      "EG",
      "ES",
      "FI",
      "FR",
      "GB",
      "GR",
      "HK",
      "HR",
      "HU",
      "ID",
      "IE",
      "IL",
      "IT",
      "KW",
      "LT",
      "LU",
      "LV",
      "MT",
      "MX",
      "NL",
      "NZ",
      "PH",
      "PL",
      "PT",
      "PY",
      "RO",
      "SA",
      "SE",
      "SG",
      "SI",
      "SK",
      "US"
    ],
    "discount": "10 $",
    "types": [
      {
        "id": 2,
        "name": "Order discount"
      }
    ],
    "image": "http://cdn.admitad.com/campaign/images/2025/9/5/20543-75ebe1c2bc996c2b.svg",
    "species": "action",
    "categories": [
      {
        "id": 8,
        "name": "Computers & Electronics"
      }
    ],
    "name": "$10 off on REDMAGIC 9 Pro with Gamepad 1 Bundle",
    "language": "en",
    "is_unique": false,
    "is_personal": false,
    "is_tracking_promo_code": false,
    "customer_type": null,
    "has_affiliate_link": true,
    "promocode": "NOT REQUIRED",
    "frameset_link": "https://yyczo.com/coupon/5e6bav9qk35af0702a2756637026d8/",
    "goto_link": "https://yyczo.com/g/tkpp3pxte85af0702a2756637026d8/?i=3"
  },
  {
    "status": "active",
    "rating": "0.00",
    "campaign": {
      "id": 20543,
      "name": "Redmagic WW",
      "site_url": "https://global.redmagic.gg/"
    },
    "description": "",
    "short_name": "$5 off on REDMAGIC 9 Pro with Screen Protector Bundle",
    "exclusive": false,
    "date_end": null,
    "date_start": "2024-04-17T00:00:00",
    "id": 748702,
    "regions": [
      "AE",
      "AT",
      "AU",
      "BE",
      "BG",
      "BR",
      "CA",
      "CL",
      "CY",
      "CZ",
      "DE",
      "DK",
      "EE",
      "EG",
      "ES",
      "FI",
      "FR",
      "GB",
      "GR",
      "HK",
      "HR",
      "HU",
      "ID",
      "IE",
      "IL",
      "IT",
      "KW",
      "LT",
      "LU",
      "LV",
      "MT",
      "MX",
      "NL",
      "NZ",
      "PH",
      "PL",
      "PT",
      "PY",
      "RO",
      "SA",
      "SE",
      "SG",
      "SI",
      "SK",
      "US"
    ],
    "discount": "5 $",
    "types": [
      {
        "id": 2,
        "name": "Order discount"
      }
    ],
    "image": "http://cdn.admitad.com/campaign/images/2025/9/5/20543-75ebe1c2bc996c2b.svg",
    "species": "action",
    "categories": [
      {
        "id": 8,
        "name": "Computers & Electronics"
      }
    ],
    "name": "$5 off on REDMAGIC 9 Pro with Screen Protector Bundle",
    "language": "en",
    "is_unique": false,
    "is_personal": false,
    "is_tracking_promo_code": false,
    "customer_type": null,
    "has_affiliate_link": true,
    "promocode": "NOT REQUIRED",
    "frameset_link": "https://yyczo.com/coupon/ts6fe7x4nh5af0702a2756637026d8/",
    "goto_link": "https://yyczo.com/g/rkeyk7ue0j5af0702a2756637026d8/?i=3"
  },
  {
    "status": "active",
    "rating": "0.00",
    "campaign": {
      "id": 20543,
      "name": "Redmagic WW",
      "site_url": "https://global.redmagic.gg/"
    },
    "description": "",
    "short_name": "$5 off on REDMAGIC 9 Pro with Protective Case Bundle",
    "exclusive": false,
    "date_end": null,
    "date_start": "2024-04-17T00:00:00",
    "id": 748701,
    "regions": [
      "AE",
      "AT",
      "AU",
      "BE",
      "BG",
      "BR",
      "CA",
      "CL",
      "CY",
      "CZ",
      "DE",
      "DK",
      "EE",
      "EG",
      "ES",
      "FI",
      "FR",
      "GB",
      "GR",
      "HK",
      "HR",
      "HU",
      "ID",
      "IE",
      "IL",
      "IT",
      "KW",
      "LT",
      "LU",
      "LV",
      "MT",
      "MX",
      "NL",
      "NZ",
      "PH",
      "PL",
      "PT",
      "PY",
      "RO",
      "SA",
      "SE",
      "SG",
      "SI",
      "SK",
      "US"
    ],
    "discount": "5 $",
    "types": [
      {
        "id": 2,
        "name": "Order discount"
      }
    ],
    "image": "http://cdn.admitad.com/campaign/images/2025/9/5/20543-75ebe1c2bc996c2b.svg",
    "species": "action",
    "categories": [
      {
        "id": 8,
        "name": "Computers & Electronics"
      }
    ],
    "name": "$5 off on REDMAGIC 9 Pro with Protective Case Bundle",
    "language": "en",
    "is_unique": false,
    "is_personal": false,
    "is_tracking_promo_code": false,
    "customer_type": null,
    "has_affiliate_link": true,
    "promocode": "NOT REQUIRED",
    "frameset_link": "https://yyczo.com/coupon/nhr1qet8gl5af0702a2756637026d8/",
    "goto_link": "https://yyczo.com/g/kx8wgs4q3g5af0702a2756637026d8/?i=3"
  },
  {
    "status": "active",
    "rating": "0.00",
    "campaign": {
      "id": 20543,
      "name": "Redmagic WW",
      "site_url": "https://global.redmagic.gg/"
    },
    "description": "",
    "short_name": "$5 off on REDMAGIC 9 Pro with Gamepad 2 Bundle",
    "exclusive": false,
    "date_end": null,
    "date_start": "2024-04-17T00:00:00",
    "id": 748700,
    "regions": [
      "AE",
      "AT",
      "AU",
      "BE",
      "BG",
      "BR",
      "CA",
      "CL",
      "CY",
      "CZ",
      "DE",
      "DK",
      "EE",
      "EG",
      "ES",
      "FI",
      "FR",
      "GB",
      "GR",
      "HK",
      "HR",
      "HU",
      "ID",
      "IE",
      "IL",
      "IT",
      "KW",
      "LT",
      "LU",
      "LV",
      "MT",
      "MX",
      "NL",
      "NZ",
      "PH",
      "PL",
      "PT",
      "PY",
      "RO",
      "SA",
      "SE",
      "SG",
      "SI",
      "SK",
      "US"
    ],
    "discount": "5 $",
    "types": [
      {
        "id": 2,
        "name": "Order discount"
      }
    ],
    "image": "http://cdn.admitad.com/campaign/images/2025/9/5/20543-75ebe1c2bc996c2b.svg",
    "species": "action",
    "categories": [
      {
        "id": 8,
        "name": "Computers & Electronics"
      }
    ],
    "name": "$5 off on REDMAGIC 9 Pro with Gamepad 2 Bundle",
    "language": "en",
    "is_unique": false,
    "is_personal": false,
    "is_tracking_promo_code": false,
    "customer_type": null,
    "has_affiliate_link": true,
    "promocode": "NOT REQUIRED",
    "frameset_link": "https://yyczo.com/coupon/iblksg4fjf5af0702a2756637026d8/",
    "goto_link": "https://yyczo.com/g/c2vqx6bcn55af0702a2756637026d8/?i=3"
  },
  {
    "status": "active",
    "rating": "0.00",
    "campaign": {
      "id": 20543,
      "name": "Redmagic WW",
      "site_url": "https://global.redmagic.gg/"
    },
    "description": "",
    "short_name": "40% off on REDMAGIC Gaming Mouse Pad",
    "exclusive": false,
    "date_end": null,
    "date_start": "2024-04-17T00:00:00",
    "id": 748699,
    "regions": [
      "AE",
      "AT",
      "AU",
      "BE",
      "BG",
      "BR",
      "CA",
      "CL",
      "CY",
      "CZ",
      "DE",
      "DK",
      "EE",
      "EG",
      "ES",
      "FI",
      "FR",
      "GB",
      "GR",
      "HK",
      "HR",
      "HU",
      "ID",
      "IE",
      "IL",
      "IT",
      "KW",
      "LT",
      "LU",
      "LV",
      "MT",
      "MX",
      "NL",
      "NZ",
      "PH",
      "PL",
      "PT",
      "PY",
      "RO",
      "SA",
      "SE",
      "SG",
      "SI",
      "SK",
      "US"
    ],
    "discount": "40%",
    "types": [
      {
        "id": 2,
        "name": "Order discount"
      }
    ],
    "image": "http://cdn.admitad.com/campaign/images/2025/9/5/20543-75ebe1c2bc996c2b.svg",
    "species": "action",
    "categories": [
      {
        "id": 8,
        "name": "Computers & Electronics"
      }
    ],
    "name": "40% off on REDMAGIC Gaming Mouse Pad",
    "language": "en",
    "is_unique": false,
    "is_personal": false,
    "is_tracking_promo_code": false,
    "customer_type": null,
    "has_affiliate_link": true,
    "promocode": "NOT REQUIRED",
    "frameset_link": "https://yyczo.com/coupon/laqx5bsyyu5af0702a2756637026d8/",
    "goto_link": "https://yyczo.com/g/xyg7832gqm5af0702a2756637026d8/?i=3"
  },
  {
    "status": "active",
    "rating": "0.00",
    "campaign": {
      "id": 20543,
      "name": "Redmagic WW",
      "site_url": "https://global.redmagic.gg/"
    },
    "description": "",
    "short_name": "30% off on REDMAGIC Gaming Mouse",
    "exclusive": false,
    "date_end": null,
    "date_start": "2024-04-17T00:00:00",
    "id": 748698,
    "regions": [
      "AE",
      "AT",
      "AU",
      "BE",
      "BG",
      "BR",
      "CA",
      "CL",
      "CY",
      "CZ",
      "DE",
      "DK",
      "EE",
      "EG",
      "ES",
      "FI",
      "FR",
      "GB",
      "GR",
      "HK",
      "HR",
      "HU",
      "ID",
      "IE",
      "IL",
      "IT",
      "KW",
      "LT",
      "LU",
      "LV",
      "MT",
      "MX",
      "NL",
      "NZ",
      "PH",
      "PL",
      "PT",
      "PY",
      "RO",
      "SA",
      "SE",
      "SG",
      "SI",
      "SK",
      "US"
    ],
    "discount": "30%",
    "types": [
      {
        "id": 2,
        "name": "Order discount"
      }
    ],
    "image": "http://cdn.admitad.com/campaign/images/2025/9/5/20543-75ebe1c2bc996c2b.svg",
    "species": "action",
    "categories": [
      {
        "id": 8,
        "name": "Computers & Electronics"
      }
    ],
    "name": "30% off on REDMAGIC Gaming Mouse",
    "language": "en",
    "is_unique": false,
    "is_personal": false,
    "is_tracking_promo_code": false,
    "customer_type": null,
    "has_affiliate_link": true,
    "promocode": "NOT REQUIRED",
    "frameset_link": "https://yyczo.com/coupon/e93xaelfjm5af0702a2756637026d8/",
    "goto_link": "https://yyczo.com/g/jkq0oo2s555af0702a2756637026d8/?i=3"
  },
  {
    "status": "active",
    "rating": "0.00",
    "campaign": {
      "id": 20543,
      "name": "Redmagic WW",
      "site_url": "https://global.redmagic.gg/"
    },
    "description": "",
    "short_name": "20% off on REDMAGIC Mechanical Keyboard",
    "exclusive": false,
    "date_end": null,
    "date_start": "2024-04-17T00:00:00",
    "id": 748697,
    "regions": [
      "AE",
      "AT",
      "AU",
      "BE",
      "BG",
      "BR",
      "CA",
      "CL",
      "CY",
      "CZ",
      "DE",
      "DK",
      "EE",
      "EG",
      "ES",
      "FI",
      "FR",
      "GB",
      "GR",
      "HK",
      "HR",
      "HU",
      "ID",
      "IE",
      "IL",
      "IT",
      "KW",
      "LT",
      "LU",
      "LV",
      "MT",
      "MX",
      "NL",
      "NZ",
      "PH",
      "PL",
      "PT",
      "PY",
      "RO",
      "SA",
      "SE",
      "SG",
      "SI",
      "SK",
      "US"
    ],
    "discount": "20%",
    "types": [
      {
        "id": 2,
        "name": "Order discount"
      }
    ],
    "image": "http://cdn.admitad.com/campaign/images/2025/9/5/20543-75ebe1c2bc996c2b.svg",
    "species": "action",
    "categories": [
      {
        "id": 8,
        "name": "Computers & Electronics"
      }
    ],
    "name": "20% off on REDMAGIC Mechanical Keyboard",
    "language": "en",
    "is_unique": false,
    "is_personal": false,
    "is_tracking_promo_code": false,
    "customer_type": null,
    "has_affiliate_link": true,
    "promocode": "NOT REQUIRED",
    "frameset_link": "https://yyczo.com/coupon/rn8m7ky73o5af0702a2756637026d8/",
    "goto_link": "https://yyczo.com/g/xz7s12pzn75af0702a2756637026d8/?i=3"
  },
  {
    "status": "active",
    "rating": "0.01",
    "campaign": {
      "id": 20543,
      "name": "Redmagic WW",
      "site_url": "https://global.redmagic.gg/"
    },
    "description": "Promo Code is not required",
    "short_name": "$10 off code for REDMAGIC 7 series phones",
    "exclusive": false,
    "date_end": null,
    "date_start": "2023-03-28T08:36:06",
    "id": 529983,
    "regions": [
      "AE",
      "AT",
      "AU",
      "BE",
      "BG",
      "BR",
      "CA",
      "CL",
      "CY",
      "CZ",
      "DE",
      "DK",
      "EE",
      "EG",
      "ES",
      "FI",
      "FR",
      "GB",
      "GR",
      "HK",
      "HR",
      "HU",
      "ID",
      "IE",
      "IL",
      "IT",
      "KW",
      "LT",
      "LU",
      "LV",
      "MT",
      "MX",
      "NL",
      "NZ",
      "PH",
      "PL",
      "PT",
      "PY",
      "RO",
      "SA",
      "SE",
      "SG",
      "SI",
      "SK",
      "US"
    ],
    "discount": "10 $",
    "types": [
      {
        "id": 2,
        "name": "Order discount"
      }
    ],
    "image": "http://cdn.admitad.com/campaign/images/2025/9/5/20543-75ebe1c2bc996c2b.svg",
    "species": "promocode",
    "categories": [
      {
        "id": 8,
        "name": "Computers & Electronics"
      },
      {
        "id": 19,
        "name": "Games"
      }
    ],
    "name": "$10 off code for REDMAGIC 7 series phones",
    "language": "en",
    "is_unique": false,
    "is_personal": false,
    "is_tracking_promo_code": false,
    "customer_type": null,
    "has_affiliate_link": true,
    "promocode": "AFFRM710",
    "frameset_link": "https://yyczo.com/coupon/asztbj4w9d5af0702a2756637026d8/",
    "goto_link": "https://yyczo.com/g/5ech344ldx5af0702a2756637026d8/?i=3"
  },
  {
    "status": "active",
    "rating": "0.00",
    "campaign": {
      "id": 20543,
      "name": "Redmagic WW",
      "site_url": "https://global.redmagic.gg/"
    },
    "description": "",
    "short_name": "$5 off on REDMAGIC Turbo Cooler",
    "exclusive": false,
    "date_end": null,
    "date_start": "2024-07-04T12:22:56",
    "id": 772727,
    "regions": [
      "AE",
      "AT",
      "AU",
      "BE",
      "BG",
      "BR",
      "CA",
      "CL",
      "CY",
      "CZ",
      "DE",
      "DK",
      "EE",
      "EG",
      "ES",
      "FI",
      "FR",
      "GB",
      "GR",
      "HK",
      "HR",
      "HU",
      "ID",
      "IE",
      "IL",
      "IT",
      "KW",
      "LT",
      "LU",
      "LV",
      "MT",
      "MX",
      "NL",
      "NZ",
      "PH",
      "PL",
      "PT",
      "PY",
      "RO",
      "SA",
      "SE",
      "SG",
      "SI",
      "SK",
      "US"
    ],
    "discount": "5 $",
    "types": [
      {
        "id": 2,
        "name": "Order discount"
      }
    ],
    "image": "http://cdn.admitad.com/campaign/images/2025/9/5/20543-75ebe1c2bc996c2b.svg",
    "species": "action",
    "categories": [
      {
        "id": 8,
        "name": "Computers & Electronics"
      }
    ],
    "name": "$5 off on REDMAGIC Turbo Cooler",
    "language": "en",
    "is_unique": false,
    "is_personal": false,
    "is_tracking_promo_code": false,
    "customer_type": null,
    "has_affiliate_link": true,
    "promocode": "NOT REQUIRED",
    "frameset_link": "https://yyczo.com/coupon/w8sz9nn85n5af0702a2756637026d8/",
    "goto_link": "https://yyczo.com/g/yr0dpf848a5af0702a2756637026d8/?i=3"
  },
  {
    "status": "active",
    "rating": "0.00",
    "campaign": {
      "id": 20543,
      "name": "Redmagic WW",
      "site_url": "https://global.redmagic.gg/"
    },
    "description": "",
    "short_name": "$40 on REDMAGIC Mechanical Keyboard",
    "exclusive": false,
    "date_end": null,
    "date_start": "2024-07-04T12:14:08",
    "id": 772726,
    "regions": [
      "AE",
      "AT",
      "AU",
      "BE",
      "BG",
      "BR",
      "CA",
      "CL",
      "CY",
      "CZ",
      "DE",
      "DK",
      "EE",
      "EG",
      "ES",
      "FI",
      "FR",
      "GB",
      "GR",
      "HK",
      "HR",
      "HU",
      "ID",
      "IE",
      "IL",
      "IT",
      "KW",
      "LT",
      "LU",
      "LV",
      "MT",
      "MX",
      "NL",
      "NZ",
      "PH",
      "PL",
      "PT",
      "PY",
      "RO",
      "SA",
      "SE",
      "SG",
      "SI",
      "SK",
      "US"
    ],
    "discount": "40 $",
    "types": [
      {
        "id": 2,
        "name": "Order discount"
      }
    ],
    "image": "http://cdn.admitad.com/campaign/images/2025/9/5/20543-75ebe1c2bc996c2b.svg",
    "species": "action",
    "categories": [
      {
        "id": 8,
        "name": "Computers & Electronics"
      }
    ],
    "name": "$40 on REDMAGIC Mechanical Keyboard",
    "language": "en",
    "is_unique": false,
    "is_personal": false,
    "is_tracking_promo_code": false,
    "customer_type": null,
    "has_affiliate_link": true,
    "promocode": "NOT REQUIRED",
    "frameset_link": "https://yyczo.com/coupon/th01vr3vv75af0702a2756637026d8/",
    "goto_link": "https://yyczo.com/g/epgiwzvfy85af0702a2756637026d8/?i=3"
  },
  {
    "status": "active",
    "rating": "0.00",
    "campaign": {
      "id": 20543,
      "name": "Redmagic WW",
      "site_url": "https://global.redmagic.gg/"
    },
    "description": "",
    "short_name": "$5 off on REDMAGIC 9 Pro with VC Cooler 5 Pro Bundle",
    "exclusive": false,
    "date_end": null,
    "date_start": "2024-05-29T15:03:25",
    "id": 762247,
    "regions": [
      "AE",
      "AT",
      "AU",
      "BE",
      "BG",
      "BR",
      "CA",
      "CL",
      "CY",
      "CZ",
      "DE",
      "DK",
      "EE",
      "EG",
      "ES",
      "FI",
      "FR",
      "GB",
      "GR",
      "HK",
      "HR",
      "HU",
      "ID",
      "IE",
      "IL",
      "IT",
      "KW",
      "LT",
      "LU",
      "LV",
      "MT",
      "MX",
      "NL",
      "NZ",
      "PH",
      "PL",
      "PT",
      "PY",
      "RO",
      "SA",
      "SE",
      "SG",
      "SI",
      "SK",
      "US"
    ],
    "discount": "5 $",
    "types": [
      {
        "id": 2,
        "name": "Order discount"
      }
    ],
    "image": "http://cdn.admitad.com/campaign/images/2025/9/5/20543-75ebe1c2bc996c2b.svg",
    "species": "action",
    "categories": [
      {
        "id": 8,
        "name": "Computers & Electronics"
      },
      {
        "id": 19,
        "name": "Games"
      }
    ],
    "name": "$5 off on REDMAGIC 9 Pro with VC Cooler 5 Pro Bundle",
    "language": "en",
    "is_unique": false,
    "is_personal": false,
    "is_tracking_promo_code": false,
    "customer_type": null,
    "has_affiliate_link": true,
    "promocode": "NOT REQUIRED",
    "frameset_link": "https://yyczo.com/coupon/v2q50fozex5af0702a2756637026d8/",
    "goto_link": "https://yyczo.com/g/kf8kbeinqg5af0702a2756637026d8/?i=3"
  },
  {
    "status": "active",
    "rating": "0.00",
    "campaign": {
      "id": 20543,
      "name": "Redmagic WW",
      "site_url": "https://global.redmagic.gg/"
    },
    "description": "",
    "short_name": "REDMAGIC 4K Gaming Monitor with a FREE mouse pad",
    "exclusive": false,
    "date_end": null,
    "date_start": "2024-05-29T14:58:47",
    "id": 762246,
    "regions": [
      "AE",
      "AT",
      "AU",
      "BE",
      "BG",
      "BR",
      "CA",
      "CL",
      "CY",
      "CZ",
      "DE",
      "DK",
      "EE",
      "EG",
      "ES",
      "FI",
      "FR",
      "GB",
      "GR",
      "HK",
      "HR",
      "HU",
      "ID",
      "IE",
      "IL",
      "IT",
      "KW",
      "LT",
      "LU",
      "LV",
      "MT",
      "MX",
      "NL",
      "NZ",
      "PH",
      "PL",
      "PT",
      "PY",
      "RO",
      "SA",
      "SE",
      "SG",
      "SI",
      "SK",
      "US"
    ],
    "discount": null,
    "types": [
      {
        "id": 3,
        "name": "Gift for an order"
      }
    ],
    "image": "http://cdn.admitad.com/campaign/images/2025/9/5/20543-75ebe1c2bc996c2b.svg",
    "species": "promocode",
    "categories": [
      {
        "id": 8,
        "name": "Computers & Electronics"
      },
      {
        "id": 19,
        "name": "Games"
      }
    ],
    "name": "REDMAGIC 4K Gaming Monitor with a FREE mouse pad",
    "language": "en",
    "is_unique": false,
    "is_personal": false,
    "is_tracking_promo_code": false,
    "customer_type": null,
    "has_affiliate_link": true,
    "promocode": "RMFMP",
    "frameset_link": "https://yyczo.com/coupon/2ie4ezu18e5af0702a2756637026d8/",
    "goto_link": "https://yyczo.com/g/du65wesc5q5af0702a2756637026d8/?i=3"
  },
  {
    "status": "active",
    "rating": "0.00",
    "campaign": {
      "id": 20543,
      "name": "Redmagic WW",
      "site_url": "https://global.redmagic.gg/"
    },
    "description": "",
    "short_name": "$10 off on REDMAGIC 9 Pro with Gamepad 1 Bundle",
    "exclusive": false,
    "date_end": null,
    "date_start": "2024-05-14T15:08:26",
    "id": 756495,
    "regions": [
      "AE",
      "AT",
      "AU",
      "BE",
      "BG",
      "BR",
      "CA",
      "CL",
      "CY",
      "CZ",
      "DE",
      "DK",
      "EE",
      "EG",
      "ES",
      "FI",
      "FR",
      "GB",
      "GR",
      "HK",
      "HR",
      "HU",
      "ID",
      "IE",
      "IL",
      "IT",
      "KW",
      "LT",
      "LU",
      "LV",
      "MT",
      "MX",
      "NL",
      "NZ",
      "PH",
      "PL",
      "PT",
      "PY",
      "RO",
      "SA",
      "SE",
      "SG",
      "SI",
      "SK",
      "US"
    ],
    "discount": "10 $",
    "types": [
      {
        "id": 2,
        "name": "Order discount"
      }
    ],
    "image": "http://cdn.admitad.com/campaign/images/2025/9/5/20543-75ebe1c2bc996c2b.svg",
    "species": "action",
    "categories": [
      {
        "id": 8,
        "name": "Computers & Electronics"
      }
    ],
    "name": "$10 off on REDMAGIC 9 Pro with Gamepad 1 Bundle",
    "language": "en",
    "is_unique": false,
    "is_personal": false,
    "is_tracking_promo_code": false,
    "customer_type": null,
    "has_affiliate_link": true,
    "promocode": "NOT REQUIRED",
    "frameset_link": "https://yyczo.com/coupon/5e6bav9qk35af0702a2756637026d8/",
    "goto_link": "https://yyczo.com/g/tkpp3pxte85af0702a2756637026d8/?i=3"
  },
  {
    "status": "active",
    "rating": "0.00",
    "campaign": {
      "id": 20543,
      "name": "Redmagic WW",
      "site_url": "https://global.redmagic.gg/"
    },
    "description": "",
    "short_name": "$5 off on REDMAGIC 9 Pro with Screen Protector Bundle",
    "exclusive": false,
    "date_end": null,
    "date_start": "2024-04-17T00:00:00",
    "id": 748702,
    "regions": [
      "AE",
      "AT",
      "AU",
      "BE",
      "BG",
      "BR",
      "CA",
      "CL",
      "CY",
      "CZ",
      "DE",
      "DK",
      "EE",
      "EG",
      "ES",
      "FI",
      "FR",
      "GB",
      "GR",
      "HK",
      "HR",
      "HU",
      "ID",
      "IE",
      "IL",
      "IT",
      "KW",
      "LT",
      "LU",
      "LV",
      "MT",
      "MX",
      "NL",
      "NZ",
      "PH",
      "PL",
      "PT",
      "PY",
      "RO",
      "SA",
      "SE",
      "SG",
      "SI",
      "SK",
      "US"
    ],
    "discount": "5 $",
    "types": [
      {
        "id": 2,
        "name": "Order discount"
      }
    ],
    "image": "http://cdn.admitad.com/campaign/images/2025/9/5/20543-75ebe1c2bc996c2b.svg",
    "species": "action",
    "categories": [
      {
        "id": 8,
        "name": "Computers & Electronics"
      }
    ],
    "name": "$5 off on REDMAGIC 9 Pro with Screen Protector Bundle",
    "language": "en",
    "is_unique": false,
    "is_personal": false,
    "is_tracking_promo_code": false,
    "customer_type": null,
    "has_affiliate_link": true,
    "promocode": "NOT REQUIRED",
    "frameset_link": "https://yyczo.com/coupon/ts6fe7x4nh5af0702a2756637026d8/",
    "goto_link": "https://yyczo.com/g/rkeyk7ue0j5af0702a2756637026d8/?i=3"
  },
  {
    "status": "active",
    "rating": "0.00",
    "campaign": {
      "id": 20543,
      "name": "Redmagic WW",
      "site_url": "https://global.redmagic.gg/"
    },
    "description": "",
    "short_name": "$5 off on REDMAGIC 9 Pro with Protective Case Bundle",
    "exclusive": false,
    "date_end": null,
    "date_start": "2024-04-17T00:00:00",
    "id": 748701,
    "regions": [
      "AE",
      "AT",
      "AU",
      "BE",
      "BG",
      "BR",
      "CA",
      "CL",
      "CY",
      "CZ",
      "DE",
      "DK",
      "EE",
      "EG",
      "ES",
      "FI",
      "FR",
      "GB",
      "GR",
      "HK",
      "HR",
      "HU",
      "ID",
      "IE",
      "IL",
      "IT",
      "KW",
      "LT",
      "LU",
      "LV",
      "MT",
      "MX",
      "NL",
      "NZ",
      "PH",
      "PL",
      "PT",
      "PY",
      "RO",
      "SA",
      "SE",
      "SG",
      "SI",
      "SK",
      "US"
    ],
    "discount": "5 $",
    "types": [
      {
        "id": 2,
        "name": "Order discount"
      }
    ],
    "image": "http://cdn.admitad.com/campaign/images/2025/9/5/20543-75ebe1c2bc996c2b.svg",
    "species": "action",
    "categories": [
      {
        "id": 8,
        "name": "Computers & Electronics"
      }
    ],
    "name": "$5 off on REDMAGIC 9 Pro with Protective Case Bundle",
    "language": "en",
    "is_unique": false,
    "is_personal": false,
    "is_tracking_promo_code": false,
    "customer_type": null,
    "has_affiliate_link": true,
    "promocode": "NOT REQUIRED",
    "frameset_link": "https://yyczo.com/coupon/nhr1qet8gl5af0702a2756637026d8/",
    "goto_link": "https://yyczo.com/g/kx8wgs4q3g5af0702a2756637026d8/?i=3"
  },
  {
    "status": "active",
    "rating": "0.00",
    "campaign": {
      "id": 20543,
      "name": "Redmagic WW",
      "site_url": "https://global.redmagic.gg/"
    },
    "description": "",
    "short_name": "$5 off on REDMAGIC 9 Pro with Gamepad 2 Bundle",
    "exclusive": false,
    "date_end": null,
    "date_start": "2024-04-17T00:00:00",
    "id": 748700,
    "regions": [
      "AE",
      "AT",
      "AU",
      "BE",
      "BG",
      "BR",
      "CA",
      "CL",
      "CY",
      "CZ",
      "DE",
      "DK",
      "EE",
      "EG",
      "ES",
      "FI",
      "FR",
      "GB",
      "GR",
      "HK",
      "HR",
      "HU",
      "ID",
      "IE",
      "IL",
      "IT",
      "KW",
      "LT",
      "LU",
      "LV",
      "MT",
      "MX",
      "NL",
      "NZ",
      "PH",
      "PL",
      "PT",
      "PY",
      "RO",
      "SA",
      "SE",
      "SG",
      "SI",
      "SK",
      "US"
    ],
    "discount": "5 $",
    "types": [
      {
        "id": 2,
        "name": "Order discount"
      }
    ],
    "image": "http://cdn.admitad.com/campaign/images/2025/9/5/20543-75ebe1c2bc996c2b.svg",
    "species": "action",
    "categories": [
      {
        "id": 8,
        "name": "Computers & Electronics"
      }
    ],
    "name": "$5 off on REDMAGIC 9 Pro with Gamepad 2 Bundle",
    "language": "en",
    "is_unique": false,
    "is_personal": false,
    "is_tracking_promo_code": false,
    "customer_type": null,
    "has_affiliate_link": true,
    "promocode": "NOT REQUIRED",
    "frameset_link": "https://yyczo.com/coupon/iblksg4fjf5af0702a2756637026d8/",
    "goto_link": "https://yyczo.com/g/c2vqx6bcn55af0702a2756637026d8/?i=3"
  },
  {
    "status": "active",
    "rating": "0.00",
    "campaign": {
      "id": 20543,
      "name": "Redmagic WW",
      "site_url": "https://global.redmagic.gg/"
    },
    "description": "",
    "short_name": "40% off on REDMAGIC Gaming Mouse Pad",
    "exclusive": false,
    "date_end": null,
    "date_start": "2024-04-17T00:00:00",
    "id": 748699,
    "regions": [
      "AE",
      "AT",
      "AU",
      "BE",
      "BG",
      "BR",
      "CA",
      "CL",
      "CY",
      "CZ",
      "DE",
      "DK",
      "EE",
      "EG",
      "ES",
      "FI",
      "FR",
      "GB",
      "GR",
      "HK",
      "HR",
      "HU",
      "ID",
      "IE",
      "IL",
      "IT",
      "KW",
      "LT",
      "LU",
      "LV",
      "MT",
      "MX",
      "NL",
      "NZ",
      "PH",
      "PL",
      "PT",
      "PY",
      "RO",
      "SA",
      "SE",
      "SG",
      "SI",
      "SK",
      "US"
    ],
    "discount": "40%",
    "types": [
      {
        "id": 2,
        "name": "Order discount"
      }
    ],
    "image": "http://cdn.admitad.com/campaign/images/2025/9/5/20543-75ebe1c2bc996c2b.svg",
    "species": "action",
    "categories": [
      {
        "id": 8,
        "name": "Computers & Electronics"
      }
    ],
    "name": "40% off on REDMAGIC Gaming Mouse Pad",
    "language": "en",
    "is_unique": false,
    "is_personal": false,
    "is_tracking_promo_code": false,
    "customer_type": null,
    "has_affiliate_link": true,
    "promocode": "NOT REQUIRED",
    "frameset_link": "https://yyczo.com/coupon/laqx5bsyyu5af0702a2756637026d8/",
    "goto_link": "https://yyczo.com/g/xyg7832gqm5af0702a2756637026d8/?i=3"
  },
  {
    "status": "active",
    "rating": "0.00",
    "campaign": {
      "id": 20543,
      "name": "Redmagic WW",
      "site_url": "https://global.redmagic.gg/"
    },
    "description": "",
    "short_name": "30% off on REDMAGIC Gaming Mouse",
    "exclusive": false,
    "date_end": null,
    "date_start": "2024-04-17T00:00:00",
    "id": 748698,
    "regions": [
      "AE",
      "AT",
      "AU",
      "BE",
      "BG",
      "BR",
      "CA",
      "CL",
      "CY",
      "CZ",
      "DE",
      "DK",
      "EE",
      "EG",
      "ES",
      "FI",
      "FR",
      "GB",
      "GR",
      "HK",
      "HR",
      "HU",
      "ID",
      "IE",
      "IL",
      "IT",
      "KW",
      "LT",
      "LU",
      "LV",
      "MT",
      "MX",
      "NL",
      "NZ",
      "PH",
      "PL",
      "PT",
      "PY",
      "RO",
      "SA",
      "SE",
      "SG",
      "SI",
      "SK",
      "US"
    ],
    "discount": "30%",
    "types": [
      {
        "id": 2,
        "name": "Order discount"
      }
    ],
    "image": "http://cdn.admitad.com/campaign/images/2025/9/5/20543-75ebe1c2bc996c2b.svg",
    "species": "action",
    "categories": [
      {
        "id": 8,
        "name": "Computers & Electronics"
      }
    ],
    "name": "30% off on REDMAGIC Gaming Mouse",
    "language": "en",
    "is_unique": false,
    "is_personal": false,
    "is_tracking_promo_code": false,
    "customer_type": null,
    "has_affiliate_link": true,
    "promocode": "NOT REQUIRED",
    "frameset_link": "https://yyczo.com/coupon/e93xaelfjm5af0702a2756637026d8/",
    "goto_link": "https://yyczo.com/g/jkq0oo2s555af0702a2756637026d8/?i=3"
  },
  {
    "status": "active",
    "rating": "0.00",
    "campaign": {
      "id": 20543,
      "name": "Redmagic WW",
      "site_url": "https://global.redmagic.gg/"
    },
    "description": "",
    "short_name": "20% off on REDMAGIC Mechanical Keyboard",
    "exclusive": false,
    "date_end": null,
    "date_start": "2024-04-17T00:00:00",
    "id": 748697,
    "regions": [
      "AE",
      "AT",
      "AU",
      "BE",
      "BG",
      "BR",
      "CA",
      "CL",
      "CY",
      "CZ",
      "DE",
      "DK",
      "EE",
      "EG",
      "ES",
      "FI",
      "FR",
      "GB",
      "GR",
      "HK",
      "HR",
      "HU",
      "ID",
      "IE",
      "IL",
      "IT",
      "KW",
      "LT",
      "LU",
      "LV",
      "MT",
      "MX",
      "NL",
      "NZ",
      "PH",
      "PL",
      "PT",
      "PY",
      "RO",
      "SA",
      "SE",
      "SG",
      "SI",
      "SK",
      "US"
    ],
    "discount": "20%",
    "types": [
      {
        "id": 2,
        "name": "Order discount"
      }
    ],
    "image": "http://cdn.admitad.com/campaign/images/2025/9/5/20543-75ebe1c2bc996c2b.svg",
    "species": "action",
    "categories": [
      {
        "id": 8,
        "name": "Computers & Electronics"
      }
    ],
    "name": "20% off on REDMAGIC Mechanical Keyboard",
    "language": "en",
    "is_unique": false,
    "is_personal": false,
    "is_tracking_promo_code": false,
    "customer_type": null,
    "has_affiliate_link": true,
    "promocode": "NOT REQUIRED",
    "frameset_link": "https://yyczo.com/coupon/rn8m7ky73o5af0702a2756637026d8/",
    "goto_link": "https://yyczo.com/g/xz7s12pzn75af0702a2756637026d8/?i=3"
  },
  {
    "status": "active",
    "rating": "0.01",
    "campaign": {
      "id": 20543,
      "name": "Redmagic WW",
      "site_url": "https://global.redmagic.gg/"
    },
    "description": "Promo Code is not required",
    "short_name": "$10 off code for REDMAGIC 7 series phones",
    "exclusive": false,
    "date_end": null,
    "date_start": "2023-03-28T08:36:06",
    "id": 529983,
    "regions": [
      "AE",
      "AT",
      "AU",
      "BE",
      "BG",
      "BR",
      "CA",
      "CL",
      "CY",
      "CZ",
      "DE",
      "DK",
      "EE",
      "EG",
      "ES",
      "FI",
      "FR",
      "GB",
      "GR",
      "HK",
      "HR",
      "HU",
      "ID",
      "IE",
      "IL",
      "IT",
      "KW",
      "LT",
      "LU",
      "LV",
      "MT",
      "MX",
      "NL",
      "NZ",
      "PH",
      "PL",
      "PT",
      "PY",
      "RO",
      "SA",
      "SE",
      "SG",
      "SI",
      "SK",
      "US"
    ],
    "discount": "10 $",
    "types": [
      {
        "id": 2,
        "name": "Order discount"
      }
    ],
    "image": "http://cdn.admitad.com/campaign/images/2025/9/5/20543-75ebe1c2bc996c2b.svg",
    "species": "promocode",
    "categories": [
      {
        "id": 8,
        "name": "Computers & Electronics"
      },
      {
        "id": 19,
        "name": "Games"
      }
    ],
    "name": "$10 off code for REDMAGIC 7 series phones",
    "language": "en",
    "is_unique": false,
    "is_personal": false,
    "is_tracking_promo_code": false,
    "customer_type": null,
    "has_affiliate_link": true,
    "promocode": "AFFRM710",
    "frameset_link": "https://yyczo.com/coupon/asztbj4w9d5af0702a2756637026d8/",
    "goto_link": "https://yyczo.com/g/5ech344ldx5af0702a2756637026d8/?i=3"
  },
  {
    "status": "active",
    "rating": "0.00",
    "campaign": {
      "id": 20543,
      "name": "Redmagic WW",
      "site_url": "https://global.redmagic.gg/"
    },
    "description": "",
    "short_name": "$5 off on REDMAGIC Turbo Cooler",
    "exclusive": false,
    "date_end": null,
    "date_start": "2024-07-04T12:22:56",
    "id": 772727,
    "regions": [
      "AE",
      "AT",
      "AU",
      "BE",
      "BG",
      "BR",
      "CA",
      "CL",
      "CY",
      "CZ",
      "DE",
      "DK",
      "EE",
      "EG",
      "ES",
      "FI",
      "FR",
      "GB",
      "GR",
      "HK",
      "HR",
      "HU",
      "ID",
      "IE",
      "IL",
      "IT",
      "KW",
      "LT",
      "LU",
      "LV",
      "MT",
      "MX",
      "NL",
      "NZ",
      "PH",
      "PL",
      "PT",
      "PY",
      "RO",
      "SA",
      "SE",
      "SG",
      "SI",
      "SK",
      "US"
    ],
    "discount": "5 $",
    "types": [
      {
        "id": 2,
        "name": "Order discount"
      }
    ],
    "image": "http://cdn.admitad.com/campaign/images/2025/9/5/20543-75ebe1c2bc996c2b.svg",
    "species": "action",
    "categories": [
      {
        "id": 8,
        "name": "Computers & Electronics"
      }
    ],
    "name": "$5 off on REDMAGIC Turbo Cooler",
    "language": "en",
    "is_unique": false,
    "is_personal": false,
    "is_tracking_promo_code": false,
    "customer_type": null,
    "has_affiliate_link": true,
    "promocode": "NOT REQUIRED",
    "frameset_link": "https://yyczo.com/coupon/w8sz9nn85n5af0702a2756637026d8/",
    "goto_link": "https://yyczo.com/g/yr0dpf848a5af0702a2756637026d8/?i=3"
  },
  {
    "status": "active",
    "rating": "0.00",
    "campaign": {
      "id": 20543,
      "name": "Redmagic WW",
      "site_url": "https://global.redmagic.gg/"
    },
    "description": "",
    "short_name": "$40 on REDMAGIC Mechanical Keyboard",
    "exclusive": false,
    "date_end": null,
    "date_start": "2024-07-04T12:14:08",
    "id": 772726,
    "regions": [
      "AE",
      "AT",
      "AU",
      "BE",
      "BG",
      "BR",
      "CA",
      "CL",
      "CY",
      "CZ",
      "DE",
      "DK",
      "EE",
      "EG",
      "ES",
      "FI",
      "FR",
      "GB",
      "GR",
      "HK",
      "HR",
      "HU",
      "ID",
      "IE",
      "IL",
      "IT",
      "KW",
      "LT",
      "LU",
      "LV",
      "MT",
      "MX",
      "NL",
      "NZ",
      "PH",
      "PL",
      "PT",
      "PY",
      "RO",
      "SA",
      "SE",
      "SG",
      "SI",
      "SK",
      "US"
    ],
    "discount": "40 $",
    "types": [
      {
        "id": 2,
        "name": "Order discount"
      }
    ],
    "image": "http://cdn.admitad.com/campaign/images/2025/9/5/20543-75ebe1c2bc996c2b.svg",
    "species": "action",
    "categories": [
      {
        "id": 8,
        "name": "Computers & Electronics"
      }
    ],
    "name": "$40 on REDMAGIC Mechanical Keyboard",
    "language": "en",
    "is_unique": false,
    "is_personal": false,
    "is_tracking_promo_code": false,
    "customer_type": null,
    "has_affiliate_link": true,
    "promocode": "NOT REQUIRED",
    "frameset_link": "https://yyczo.com/coupon/th01vr3vv75af0702a2756637026d8/",
    "goto_link": "https://yyczo.com/g/epgiwzvfy85af0702a2756637026d8/?i=3"
  },
  {
    "status": "active",
    "rating": "0.00",
    "campaign": {
      "id": 20543,
      "name": "Redmagic WW",
      "site_url": "https://global.redmagic.gg/"
    },
    "description": "",
    "short_name": "$5 off on REDMAGIC 9 Pro with VC Cooler 5 Pro Bundle",
    "exclusive": false,
    "date_end": null,
    "date_start": "2024-05-29T15:03:25",
    "id": 762247,
    "regions": [
      "AE",
      "AT",
      "AU",
      "BE",
      "BG",
      "BR",
      "CA",
      "CL",
      "CY",
      "CZ",
      "DE",
      "DK",
      "EE",
      "EG",
      "ES",
      "FI",
      "FR",
      "GB",
      "GR",
      "HK",
      "HR",
      "HU",
      "ID",
      "IE",
      "IL",
      "IT",
      "KW",
      "LT",
      "LU",
      "LV",
      "MT",
      "MX",
      "NL",
      "NZ",
      "PH",
      "PL",
      "PT",
      "PY",
      "RO",
      "SA",
      "SE",
      "SG",
      "SI",
      "SK",
      "US"
    ],
    "discount": "5 $",
    "types": [
      {
        "id": 2,
        "name": "Order discount"
      }
    ],
    "image": "http://cdn.admitad.com/campaign/images/2025/9/5/20543-75ebe1c2bc996c2b.svg",
    "species": "action",
    "categories": [
      {
        "id": 8,
        "name": "Computers & Electronics"
      },
      {
        "id": 19,
        "name": "Games"
      }
    ],
    "name": "$5 off on REDMAGIC 9 Pro with VC Cooler 5 Pro Bundle",
    "language": "en",
    "is_unique": false,
    "is_personal": false,
    "is_tracking_promo_code": false,
    "customer_type": null,
    "has_affiliate_link": true,
    "promocode": "NOT REQUIRED",
    "frameset_link": "https://yyczo.com/coupon/v2q50fozex5af0702a2756637026d8/",
    "goto_link": "https://yyczo.com/g/kf8kbeinqg5af0702a2756637026d8/?i=3"
  },
  {
    "status": "active",
    "rating": "0.00",
    "campaign": {
      "id": 20543,
      "name": "Redmagic WW",
      "site_url": "https://global.redmagic.gg/"
    },
    "description": "",
    "short_name": "REDMAGIC 4K Gaming Monitor with a FREE mouse pad",
    "exclusive": false,
    "date_end": null,
    "date_start": "2024-05-29T14:58:47",
    "id": 762246,
    "regions": [
      "AE",
      "AT",
      "AU",
      "BE",
      "BG",
      "BR",
      "CA",
      "CL",
      "CY",
      "CZ",
      "DE",
      "DK",
      "EE",
      "EG",
      "ES",
      "FI",
      "FR",
      "GB",
      "GR",
      "HK",
      "HR",
      "HU",
      "ID",
      "IE",
      "IL",
      "IT",
      "KW",
      "LT",
      "LU",
      "LV",
      "MT",
      "MX",
      "NL",
      "NZ",
      "PH",
      "PL",
      "PT",
      "PY",
      "RO",
      "SA",
      "SE",
      "SG",
      "SI",
      "SK",
      "US"
    ],
    "discount": null,
    "types": [
      {
        "id": 3,
        "name": "Gift for an order"
      }
    ],
    "image": "http://cdn.admitad.com/campaign/images/2025/9/5/20543-75ebe1c2bc996c2b.svg",
    "species": "promocode",
    "categories": [
      {
        "id": 8,
        "name": "Computers & Electronics"
      },
      {
        "id": 19,
        "name": "Games"
      }
    ],
    "name": "REDMAGIC 4K Gaming Monitor with a FREE mouse pad",
    "language": "en",
    "is_unique": false,
    "is_personal": false,
    "is_tracking_promo_code": false,
    "customer_type": null,
    "has_affiliate_link": true,
    "promocode": "RMFMP",
    "frameset_link": "https://yyczo.com/coupon/2ie4ezu18e5af0702a2756637026d8/",
    "goto_link": "https://yyczo.com/g/du65wesc5q5af0702a2756637026d8/?i=3"
  },
  {
    "status": "active",
    "rating": "0.00",
    "campaign": {
      "id": 20543,
      "name": "Redmagic WW",
      "site_url": "https://global.redmagic.gg/"
    },
    "description": "",
    "short_name": "$10 off on REDMAGIC 9 Pro with Gamepad 1 Bundle",
    "exclusive": false,
    "date_end": null,
    "date_start": "2024-05-14T15:08:26",
    "id": 756495,
    "regions": [
      "AE",
      "AT",
      "AU",
      "BE",
      "BG",
      "BR",
      "CA",
      "CL",
      "CY",
      "CZ",
      "DE",
      "DK",
      "EE",
      "EG",
      "ES",
      "FI",
      "FR",
      "GB",
      "GR",
      "HK",
      "HR",
      "HU",
      "ID",
      "IE",
      "IL",
      "IT",
      "KW",
      "LT",
      "LU",
      "LV",
      "MT",
      "MX",
      "NL",
      "NZ",
      "PH",
      "PL",
      "PT",
      "PY",
      "RO",
      "SA",
      "SE",
      "SG",
      "SI",
      "SK",
      "US"
    ],
    "discount": "10 $",
    "types": [
      {
        "id": 2,
        "name": "Order discount"
      }
    ],
    "image": "http://cdn.admitad.com/campaign/images/2025/9/5/20543-75ebe1c2bc996c2b.svg",
    "species": "action",
    "categories": [
      {
        "id": 8,
        "name": "Computers & Electronics"
      }
    ],
    "name": "$10 off on REDMAGIC 9 Pro with Gamepad 1 Bundle",
    "language": "en",
    "is_unique": false,
    "is_personal": false,
    "is_tracking_promo_code": false,
    "customer_type": null,
    "has_affiliate_link": true,
    "promocode": "NOT REQUIRED",
    "frameset_link": "https://yyczo.com/coupon/5e6bav9qk35af0702a2756637026d8/",
    "goto_link": "https://yyczo.com/g/tkpp3pxte85af0702a2756637026d8/?i=3"
  },
  {
    "status": "active",
    "rating": "0.00",
    "campaign": {
      "id": 20543,
      "name": "Redmagic WW",
      "site_url": "https://global.redmagic.gg/"
    },
    "description": "",
    "short_name": "$5 off on REDMAGIC 9 Pro with Screen Protector Bundle",
    "exclusive": false,
    "date_end": null,
    "date_start": "2024-04-17T00:00:00",
    "id": 748702,
    "regions": [
      "AE",
      "AT",
      "AU",
      "BE",
      "BG",
      "BR",
      "CA",
      "CL",
      "CY",
      "CZ",
      "DE",
      "DK",
      "EE",
      "EG",
      "ES",
      "FI",
      "FR",
      "GB",
      "GR",
      "HK",
      "HR",
      "HU",
      "ID",
      "IE",
      "IL",
      "IT",
      "KW",
      "LT",
      "LU",
      "LV",
      "MT",
      "MX",
      "NL",
      "NZ",
      "PH",
      "PL",
      "PT",
      "PY",
      "RO",
      "SA",
      "SE",
      "SG",
      "SI",
      "SK",
      "US"
    ],
    "discount": "5 $",
    "types": [
      {
        "id": 2,
        "name": "Order discount"
      }
    ],
    "image": "http://cdn.admitad.com/campaign/images/2025/9/5/20543-75ebe1c2bc996c2b.svg",
    "species": "action",
    "categories": [
      {
        "id": 8,
        "name": "Computers & Electronics"
      }
    ],
    "name": "$5 off on REDMAGIC 9 Pro with Screen Protector Bundle",
    "language": "en",
    "is_unique": false,
    "is_personal": false,
    "is_tracking_promo_code": false,
    "customer_type": null,
    "has_affiliate_link": true,
    "promocode": "NOT REQUIRED",
    "frameset_link": "https://yyczo.com/coupon/ts6fe7x4nh5af0702a2756637026d8/",
    "goto_link": "https://yyczo.com/g/rkeyk7ue0j5af0702a2756637026d8/?i=3"
  },
  {
    "status": "active",
    "rating": "0.00",
    "campaign": {
      "id": 20543,
      "name": "Redmagic WW",
      "site_url": "https://global.redmagic.gg/"
    },
    "description": "",
    "short_name": "$5 off on REDMAGIC 9 Pro with Protective Case Bundle",
    "exclusive": false,
    "date_end": null,
    "date_start": "2024-04-17T00:00:00",
    "id": 748701,
    "regions": [
      "AE",
      "AT",
      "AU",
      "BE",
      "BG",
      "BR",
      "CA",
      "CL",
      "CY",
      "CZ",
      "DE",
      "DK",
      "EE",
      "EG",
      "ES",
      "FI",
      "FR",
      "GB",
      "GR",
      "HK",
      "HR",
      "HU",
      "ID",
      "IE",
      "IL",
      "IT",
      "KW",
      "LT",
      "LU",
      "LV",
      "MT",
      "MX",
      "NL",
      "NZ",
      "PH",
      "PL",
      "PT",
      "PY",
      "RO",
      "SA",
      "SE",
      "SG",
      "SI",
      "SK",
      "US"
    ],
    "discount": "5 $",
    "types": [
      {
        "id": 2,
        "name": "Order discount"
      }
    ],
    "image": "http://cdn.admitad.com/campaign/images/2025/9/5/20543-75ebe1c2bc996c2b.svg",
    "species": "action",
    "categories": [
      {
        "id": 8,
        "name": "Computers & Electronics"
      }
    ],
    "name": "$5 off on REDMAGIC 9 Pro with Protective Case Bundle",
    "language": "en",
    "is_unique": false,
    "is_personal": false,
    "is_tracking_promo_code": false,
    "customer_type": null,
    "has_affiliate_link": true,
    "promocode": "NOT REQUIRED",
    "frameset_link": "https://yyczo.com/coupon/nhr1qet8gl5af0702a2756637026d8/",
    "goto_link": "https://yyczo.com/g/kx8wgs4q3g5af0702a2756637026d8/?i=3"
  },
  {
    "status": "active",
    "rating": "0.00",
    "campaign": {
      "id": 20543,
      "name": "Redmagic WW",
      "site_url": "https://global.redmagic.gg/"
    },
    "description": "",
    "short_name": "$5 off on REDMAGIC 9 Pro with Gamepad 2 Bundle",
    "exclusive": false,
    "date_end": null,
    "date_start": "2024-04-17T00:00:00",
    "id": 748700,
    "regions": [
      "AE",
      "AT",
      "AU",
      "BE",
      "BG",
      "BR",
      "CA",
      "CL",
      "CY",
      "CZ",
      "DE",
      "DK",
      "EE",
      "EG",
      "ES",
      "FI",
      "FR",
      "GB",
      "GR",
      "HK",
      "HR",
      "HU",
      "ID",
      "IE",
      "IL",
      "IT",
      "KW",
      "LT",
      "LU",
      "LV",
      "MT",
      "MX",
      "NL",
      "NZ",
      "PH",
      "PL",
      "PT",
      "PY",
      "RO",
      "SA",
      "SE",
      "SG",
      "SI",
      "SK",
      "US"
    ],
    "discount": "5 $",
    "types": [
      {
        "id": 2,
        "name": "Order discount"
      }
    ],
    "image": "http://cdn.admitad.com/campaign/images/2025/9/5/20543-75ebe1c2bc996c2b.svg",
    "species": "action",
    "categories": [
      {
        "id": 8,
        "name": "Computers & Electronics"
      }
    ],
    "name": "$5 off on REDMAGIC 9 Pro with Gamepad 2 Bundle",
    "language": "en",
    "is_unique": false,
    "is_personal": false,
    "is_tracking_promo_code": false,
    "customer_type": null,
    "has_affiliate_link": true,
    "promocode": "NOT REQUIRED",
    "frameset_link": "https://yyczo.com/coupon/iblksg4fjf5af0702a2756637026d8/",
    "goto_link": "https://yyczo.com/g/c2vqx6bcn55af0702a2756637026d8/?i=3"
  },
  {
    "status": "active",
    "rating": "0.00",
    "campaign": {
      "id": 20543,
      "name": "Redmagic WW",
      "site_url": "https://global.redmagic.gg/"
    },
    "description": "",
    "short_name": "40% off on REDMAGIC Gaming Mouse Pad",
    "exclusive": false,
    "date_end": null,
    "date_start": "2024-04-17T00:00:00",
    "id": 748699,
    "regions": [
      "AE",
      "AT",
      "AU",
      "BE",
      "BG",
      "BR",
      "CA",
      "CL",
      "CY",
      "CZ",
      "DE",
      "DK",
      "EE",
      "EG",
      "ES",
      "FI",
      "FR",
      "GB",
      "GR",
      "HK",
      "HR",
      "HU",
      "ID",
      "IE",
      "IL",
      "IT",
      "KW",
      "LT",
      "LU",
      "LV",
      "MT",
      "MX",
      "NL",
      "NZ",
      "PH",
      "PL",
      "PT",
      "PY",
      "RO",
      "SA",
      "SE",
      "SG",
      "SI",
      "SK",
      "US"
    ],
    "discount": "40%",
    "types": [
      {
        "id": 2,
        "name": "Order discount"
      }
    ],
    "image": "http://cdn.admitad.com/campaign/images/2025/9/5/20543-75ebe1c2bc996c2b.svg",
    "species": "action",
    "categories": [
      {
        "id": 8,
        "name": "Computers & Electronics"
      }
    ],
    "name": "40% off on REDMAGIC Gaming Mouse Pad",
    "language": "en",
    "is_unique": false,
    "is_personal": false,
    "is_tracking_promo_code": false,
    "customer_type": null,
    "has_affiliate_link": true,
    "promocode": "NOT REQUIRED",
    "frameset_link": "https://yyczo.com/coupon/laqx5bsyyu5af0702a2756637026d8/",
    "goto_link": "https://yyczo.com/g/xyg7832gqm5af0702a2756637026d8/?i=3"
  },
  {
    "status": "active",
    "rating": "0.00",
    "campaign": {
      "id": 20543,
      "name": "Redmagic WW",
      "site_url": "https://global.redmagic.gg/"
    },
    "description": "",
    "short_name": "30% off on REDMAGIC Gaming Mouse",
    "exclusive": false,
    "date_end": null,
    "date_start": "2024-04-17T00:00:00",
    "id": 748698,
    "regions": [
      "AE",
      "AT",
      "AU",
      "BE",
      "BG",
      "BR",
      "CA",
      "CL",
      "CY",
      "CZ",
      "DE",
      "DK",
      "EE",
      "EG",
      "ES",
      "FI",
      "FR",
      "GB",
      "GR",
      "HK",
      "HR",
      "HU",
      "ID",
      "IE",
      "IL",
      "IT",
      "KW",
      "LT",
      "LU",
      "LV",
      "MT",
      "MX",
      "NL",
      "NZ",
      "PH",
      "PL",
      "PT",
      "PY",
      "RO",
      "SA",
      "SE",
      "SG",
      "SI",
      "SK",
      "US"
    ],
    "discount": "30%",
    "types": [
      {
        "id": 2,
        "name": "Order discount"
      }
    ],
    "image": "http://cdn.admitad.com/campaign/images/2025/9/5/20543-75ebe1c2bc996c2b.svg",
    "species": "action",
    "categories": [
      {
        "id": 8,
        "name": "Computers & Electronics"
      }
    ],
    "name": "30% off on REDMAGIC Gaming Mouse",
    "language": "en",
    "is_unique": false,
    "is_personal": false,
    "is_tracking_promo_code": false,
    "customer_type": null,
    "has_affiliate_link": true,
    "promocode": "NOT REQUIRED",
    "frameset_link": "https://yyczo.com/coupon/e93xaelfjm5af0702a2756637026d8/",
    "goto_link": "https://yyczo.com/g/jkq0oo2s555af0702a2756637026d8/?i=3"
  },
  {
    "status": "active",
    "rating": "0.00",
    "campaign": {
      "id": 20543,
      "name": "Redmagic WW",
      "site_url": "https://global.redmagic.gg/"
    },
    "description": "",
    "short_name": "20% off on REDMAGIC Mechanical Keyboard",
    "exclusive": false,
    "date_end": null,
    "date_start": "2024-04-17T00:00:00",
    "id": 748697,
    "regions": [
      "AE",
      "AT",
      "AU",
      "BE",
      "BG",
      "BR",
      "CA",
      "CL",
      "CY",
      "CZ",
      "DE",
      "DK",
      "EE",
      "EG",
      "ES",
      "FI",
      "FR",
      "GB",
      "GR",
      "HK",
      "HR",
      "HU",
      "ID",
      "IE",
      "IL",
      "IT",
      "KW",
      "LT",
      "LU",
      "LV",
      "MT",
      "MX",
      "NL",
      "NZ",
      "PH",
      "PL",
      "PT",
      "PY",
      "RO",
      "SA",
      "SE",
      "SG",
      "SI",
      "SK",
      "US"
    ],
    "discount": "20%",
    "types": [
      {
        "id": 2,
        "name": "Order discount"
      }
    ],
    "image": "http://cdn.admitad.com/campaign/images/2025/9/5/20543-75ebe1c2bc996c2b.svg",
    "species": "action",
    "categories": [
      {
        "id": 8,
        "name": "Computers & Electronics"
      }
    ],
    "name": "20% off on REDMAGIC Mechanical Keyboard",
    "language": "en",
    "is_unique": false,
    "is_personal": false,
    "is_tracking_promo_code": false,
    "customer_type": null,
    "has_affiliate_link": true,
    "promocode": "NOT REQUIRED",
    "frameset_link": "https://yyczo.com/coupon/rn8m7ky73o5af0702a2756637026d8/",
    "goto_link": "https://yyczo.com/g/xz7s12pzn75af0702a2756637026d8/?i=3"
  },
  {
    "status": "active",
    "rating": "0.01",
    "campaign": {
      "id": 20543,
      "name": "Redmagic WW",
      "site_url": "https://global.redmagic.gg/"
    },
    "description": "Promo Code is not required",
    "short_name": "$10 off code for REDMAGIC 7 series phones",
    "exclusive": false,
    "date_end": null,
    "date_start": "2023-03-28T08:36:06",
    "id": 529983,
    "regions": [
      "AE",
      "AT",
      "AU",
      "BE",
      "BG",
      "BR",
      "CA",
      "CL",
      "CY",
      "CZ",
      "DE",
      "DK",
      "EE",
      "EG",
      "ES",
      "FI",
      "FR",
      "GB",
      "GR",
      "HK",
      "HR",
      "HU",
      "ID",
      "IE",
      "IL",
      "IT",
      "KW",
      "LT",
      "LU",
      "LV",
      "MT",
      "MX",
      "NL",
      "NZ",
      "PH",
      "PL",
      "PT",
      "PY",
      "RO",
      "SA",
      "SE",
      "SG",
      "SI",
      "SK",
      "US"
    ],
    "discount": "10 $",
    "types": [
      {
        "id": 2,
        "name": "Order discount"
      }
    ],
    "image": "http://cdn.admitad.com/campaign/images/2025/9/5/20543-75ebe1c2bc996c2b.svg",
    "species": "promocode",
    "categories": [
      {
        "id": 8,
        "name": "Computers & Electronics"
      },
      {
        "id": 19,
        "name": "Games"
      }
    ],
    "name": "$10 off code for REDMAGIC 7 series phones",
    "language": "en",
    "is_unique": false,
    "is_personal": false,
    "is_tracking_promo_code": false,
    "customer_type": null,
    "has_affiliate_link": true,
    "promocode": "AFFRM710",
    "frameset_link": "https://yyczo.com/coupon/asztbj4w9d5af0702a2756637026d8/",
    "goto_link": "https://yyczo.com/g/5ech344ldx5af0702a2756637026d8/?i=3"
  },
  {
    "status": "active",
    "rating": "0.00",
    "campaign": {
      "id": 20543,
      "name": "Redmagic WW",
      "site_url": "https://global.redmagic.gg/"
    },
    "description": "",
    "short_name": "$5 off on REDMAGIC Turbo Cooler",
    "exclusive": false,
    "date_end": null,
    "date_start": "2024-07-04T12:22:56",
    "id": 772727,
    "regions": [
      "AE",
      "AT",
      "AU",
      "BE",
      "BG",
      "BR",
      "CA",
      "CL",
      "CY",
      "CZ",
      "DE",
      "DK",
      "EE",
      "EG",
      "ES",
      "FI",
      "FR",
      "GB",
      "GR",
      "HK",
      "HR",
      "HU",
      "ID",
      "IE",
      "IL",
      "IT",
      "KW",
      "LT",
      "LU",
      "LV",
      "MT",
      "MX",
      "NL",
      "NZ",
      "PH",
      "PL",
      "PT",
      "PY",
      "RO",
      "SA",
      "SE",
      "SG",
      "SI",
      "SK",
      "US"
    ],
    "discount": "5 $",
    "types": [
      {
        "id": 2,
        "name": "Order discount"
      }
    ],
    "image": "http://cdn.admitad.com/campaign/images/2025/9/5/20543-75ebe1c2bc996c2b.svg",
    "species": "action",
    "categories": [
      {
        "id": 8,
        "name": "Computers & Electronics"
      }
    ],
    "name": "$5 off on REDMAGIC Turbo Cooler",
    "language": "en",
    "is_unique": false,
    "is_personal": false,
    "is_tracking_promo_code": false,
    "customer_type": null,
    "has_affiliate_link": true,
    "promocode": "NOT REQUIRED",
    "frameset_link": "https://yyczo.com/coupon/w8sz9nn85n5af0702a2756637026d8/",
    "goto_link": "https://yyczo.com/g/yr0dpf848a5af0702a2756637026d8/?i=3"
  },
  {
    "status": "active",
    "rating": "0.00",
    "campaign": {
      "id": 20543,
      "name": "Redmagic WW",
      "site_url": "https://global.redmagic.gg/"
    },
    "description": "",
    "short_name": "$40 on REDMAGIC Mechanical Keyboard",
    "exclusive": false,
    "date_end": null,
    "date_start": "2024-07-04T12:14:08",
    "id": 772726,
    "regions": [
      "AE",
      "AT",
      "AU",
      "BE",
      "BG",
      "BR",
      "CA",
      "CL",
      "CY",
      "CZ",
      "DE",
      "DK",
      "EE",
      "EG",
      "ES",
      "FI",
      "FR",
      "GB",
      "GR",
      "HK",
      "HR",
      "HU",
      "ID",
      "IE",
      "IL",
      "IT",
      "KW",
      "LT",
      "LU",
      "LV",
      "MT",
      "MX",
      "NL",
      "NZ",
      "PH",
      "PL",
      "PT",
      "PY",
      "RO",
      "SA",
      "SE",
      "SG",
      "SI",
      "SK",
      "US"
    ],
    "discount": "40 $",
    "types": [
      {
        "id": 2,
        "name": "Order discount"
      }
    ],
    "image": "http://cdn.admitad.com/campaign/images/2025/9/5/20543-75ebe1c2bc996c2b.svg",
    "species": "action",
    "categories": [
      {
        "id": 8,
        "name": "Computers & Electronics"
      }
    ],
    "name": "$40 on REDMAGIC Mechanical Keyboard",
    "language": "en",
    "is_unique": false,
    "is_personal": false,
    "is_tracking_promo_code": false,
    "customer_type": null,
    "has_affiliate_link": true,
    "promocode": "NOT REQUIRED",
    "frameset_link": "https://yyczo.com/coupon/th01vr3vv75af0702a2756637026d8/",
    "goto_link": "https://yyczo.com/g/epgiwzvfy85af0702a2756637026d8/?i=3"
  },
  {
    "status": "active",
    "rating": "0.00",
    "campaign": {
      "id": 20543,
      "name": "Redmagic WW",
      "site_url": "https://global.redmagic.gg/"
    },
    "description": "",
    "short_name": "$5 off on REDMAGIC 9 Pro with VC Cooler 5 Pro Bundle",
    "exclusive": false,
    "date_end": null,
    "date_start": "2024-05-29T15:03:25",
    "id": 762247,
    "regions": [
      "AE",
      "AT",
      "AU",
      "BE",
      "BG",
      "BR",
      "CA",
      "CL",
      "CY",
      "CZ",
      "DE",
      "DK",
      "EE",
      "EG",
      "ES",
      "FI",
      "FR",
      "GB",
      "GR",
      "HK",
      "HR",
      "HU",
      "ID",
      "IE",
      "IL",
      "IT",
      "KW",
      "LT",
      "LU",
      "LV",
      "MT",
      "MX",
      "NL",
      "NZ",
      "PH",
      "PL",
      "PT",
      "PY",
      "RO",
      "SA",
      "SE",
      "SG",
      "SI",
      "SK",
      "US"
    ],
    "discount": "5 $",
    "types": [
      {
        "id": 2,
        "name": "Order discount"
      }
    ],
    "image": "http://cdn.admitad.com/campaign/images/2025/9/5/20543-75ebe1c2bc996c2b.svg",
    "species": "action",
    "categories": [
      {
        "id": 8,
        "name": "Computers & Electronics"
      },
      {
        "id": 19,
        "name": "Games"
      }
    ],
    "name": "$5 off on REDMAGIC 9 Pro with VC Cooler 5 Pro Bundle",
    "language": "en",
    "is_unique": false,
    "is_personal": false,
    "is_tracking_promo_code": false,
    "customer_type": null,
    "has_affiliate_link": true,
    "promocode": "NOT REQUIRED",
    "frameset_link": "https://yyczo.com/coupon/v2q50fozex5af0702a2756637026d8/",
    "goto_link": "https://yyczo.com/g/kf8kbeinqg5af0702a2756637026d8/?i=3"
  },
  {
    "status": "active",
    "rating": "0.00",
    "campaign": {
      "id": 20543,
      "name": "Redmagic WW",
      "site_url": "https://global.redmagic.gg/"
    },
    "description": "",
    "short_name": "REDMAGIC 4K Gaming Monitor with a FREE mouse pad",
    "exclusive": false,
    "date_end": null,
    "date_start": "2024-05-29T14:58:47",
    "id": 762246,
    "regions": [
      "AE",
      "AT",
      "AU",
      "BE",
      "BG",
      "BR",
      "CA",
      "CL",
      "CY",
      "CZ",
      "DE",
      "DK",
      "EE",
      "EG",
      "ES",
      "FI",
      "FR",
      "GB",
      "GR",
      "HK",
      "HR",
      "HU",
      "ID",
      "IE",
      "IL",
      "IT",
      "KW",
      "LT",
      "LU",
      "LV",
      "MT",
      "MX",
      "NL",
      "NZ",
      "PH",
      "PL",
      "PT",
      "PY",
      "RO",
      "SA",
      "SE",
      "SG",
      "SI",
      "SK",
      "US"
    ],
    "discount": null,
    "types": [
      {
        "id": 3,
        "name": "Gift for an order"
      }
    ],
    "image": "http://cdn.admitad.com/campaign/images/2025/9/5/20543-75ebe1c2bc996c2b.svg",
    "species": "promocode",
    "categories": [
      {
        "id": 8,
        "name": "Computers & Electronics"
      },
      {
        "id": 19,
        "name": "Games"
      }
    ],
    "name": "REDMAGIC 4K Gaming Monitor with a FREE mouse pad",
    "language": "en",
    "is_unique": false,
    "is_personal": false,
    "is_tracking_promo_code": false,
    "customer_type": null,
    "has_affiliate_link": true,
    "promocode": "RMFMP",
    "frameset_link": "https://yyczo.com/coupon/2ie4ezu18e5af0702a2756637026d8/",
    "goto_link": "https://yyczo.com/g/du65wesc5q5af0702a2756637026d8/?i=3"
  },
  {
    "status": "active",
    "rating": "0.00",
    "campaign": {
      "id": 20543,
      "name": "Redmagic WW",
      "site_url": "https://global.redmagic.gg/"
    },
    "description": "",
    "short_name": "$10 off on REDMAGIC 9 Pro with Gamepad 1 Bundle",
    "exclusive": false,
    "date_end": null,
    "date_start": "2024-05-14T15:08:26",
    "id": 756495,
    "regions": [
      "AE",
      "AT",
      "AU",
      "BE",
      "BG",
      "BR",
      "CA",
      "CL",
      "CY",
      "CZ",
      "DE",
      "DK",
      "EE",
      "EG",
      "ES",
      "FI",
      "FR",
      "GB",
      "GR",
      "HK",
      "HR",
      "HU",
      "ID",
      "IE",
      "IL",
      "IT",
      "KW",
      "LT",
      "LU",
      "LV",
      "MT",
      "MX",
      "NL",
      "NZ",
      "PH",
      "PL",
      "PT",
      "PY",
      "RO",
      "SA",
      "SE",
      "SG",
      "SI",
      "SK",
      "US"
    ],
    "discount": "10 $",
    "types": [
      {
        "id": 2,
        "name": "Order discount"
      }
    ],
    "image": "http://cdn.admitad.com/campaign/images/2025/9/5/20543-75ebe1c2bc996c2b.svg",
    "species": "action",
    "categories": [
      {
        "id": 8,
        "name": "Computers & Electronics"
      }
    ],
    "name": "$10 off on REDMAGIC 9 Pro with Gamepad 1 Bundle",
    "language": "en",
    "is_unique": false,
    "is_personal": false,
    "is_tracking_promo_code": false,
    "customer_type": null,
    "has_affiliate_link": true,
    "promocode": "NOT REQUIRED",
    "frameset_link": "https://yyczo.com/coupon/5e6bav9qk35af0702a2756637026d8/",
    "goto_link": "https://yyczo.com/g/tkpp3pxte85af0702a2756637026d8/?i=3"
  },
  {
    "status": "active",
    "rating": "0.00",
    "campaign": {
      "id": 20543,
      "name": "Redmagic WW",
      "site_url": "https://global.redmagic.gg/"
    },
    "description": "",
    "short_name": "$5 off on REDMAGIC 9 Pro with Screen Protector Bundle",
    "exclusive": false,
    "date_end": null,
    "date_start": "2024-04-17T00:00:00",
    "id": 748702,
    "regions": [
      "AE",
      "AT",
      "AU",
      "BE",
      "BG",
      "BR",
      "CA",
      "CL",
      "CY",
      "CZ",
      "DE",
      "DK",
      "EE",
      "EG",
      "ES",
      "FI",
      "FR",
      "GB",
      "GR",
      "HK",
      "HR",
      "HU",
      "ID",
      "IE",
      "IL",
      "IT",
      "KW",
      "LT",
      "LU",
      "LV",
      "MT",
      "MX",
      "NL",
      "NZ",
      "PH",
      "PL",
      "PT",
      "PY",
      "RO",
      "SA",
      "SE",
      "SG",
      "SI",
      "SK",
      "US"
    ],
    "discount": "5 $",
    "types": [
      {
        "id": 2,
        "name": "Order discount"
      }
    ],
    "image": "http://cdn.admitad.com/campaign/images/2025/9/5/20543-75ebe1c2bc996c2b.svg",
    "species": "action",
    "categories": [
      {
        "id": 8,
        "name": "Computers & Electronics"
      }
    ],
    "name": "$5 off on REDMAGIC 9 Pro with Screen Protector Bundle",
    "language": "en",
    "is_unique": false,
    "is_personal": false,
    "is_tracking_promo_code": false,
    "customer_type": null,
    "has_affiliate_link": true,
    "promocode": "NOT REQUIRED",
    "frameset_link": "https://yyczo.com/coupon/ts6fe7x4nh5af0702a2756637026d8/",
    "goto_link": "https://yyczo.com/g/rkeyk7ue0j5af0702a2756637026d8/?i=3"
  },
  {
    "status": "active",
    "rating": "0.00",
    "campaign": {
      "id": 20543,
      "name": "Redmagic WW",
      "site_url": "https://global.redmagic.gg/"
    },
    "description": "",
    "short_name": "$5 off on REDMAGIC 9 Pro with Protective Case Bundle",
    "exclusive": false,
    "date_end": null,
    "date_start": "2024-04-17T00:00:00",
    "id": 748701,
    "regions": [
      "AE",
      "AT",
      "AU",
      "BE",
      "BG",
      "BR",
      "CA",
      "CL",
      "CY",
      "CZ",
      "DE",
      "DK",
      "EE",
      "EG",
      "ES",
      "FI",
      "FR",
      "GB",
      "GR",
      "HK",
      "HR",
      "HU",
      "ID",
      "IE",
      "IL",
      "IT",
      "KW",
      "LT",
      "LU",
      "LV",
      "MT",
      "MX",
      "NL",
      "NZ",
      "PH",
      "PL",
      "PT",
      "PY",
      "RO",
      "SA",
      "SE",
      "SG",
      "SI",
      "SK",
      "US"
    ],
    "discount": "5 $",
    "types": [
      {
        "id": 2,
        "name": "Order discount"
      }
    ],
    "image": "http://cdn.admitad.com/campaign/images/2025/9/5/20543-75ebe1c2bc996c2b.svg",
    "species": "action",
    "categories": [
      {
        "id": 8,
        "name": "Computers & Electronics"
      }
    ],
    "name": "$5 off on REDMAGIC 9 Pro with Protective Case Bundle",
    "language": "en",
    "is_unique": false,
    "is_personal": false,
    "is_tracking_promo_code": false,
    "customer_type": null,
    "has_affiliate_link": true,
    "promocode": "NOT REQUIRED",
    "frameset_link": "https://yyczo.com/coupon/nhr1qet8gl5af0702a2756637026d8/",
    "goto_link": "https://yyczo.com/g/kx8wgs4q3g5af0702a2756637026d8/?i=3"
  },
  {
    "status": "active",
    "rating": "0.00",
    "campaign": {
      "id": 20543,
      "name": "Redmagic WW",
      "site_url": "https://global.redmagic.gg/"
    },
    "description": "",
    "short_name": "$5 off on REDMAGIC 9 Pro with Gamepad 2 Bundle",
    "exclusive": false,
    "date_end": null,
    "date_start": "2024-04-17T00:00:00",
    "id": 748700,
    "regions": [
      "AE",
      "AT",
      "AU",
      "BE",
      "BG",
      "BR",
      "CA",
      "CL",
      "CY",
      "CZ",
      "DE",
      "DK",
      "EE",
      "EG",
      "ES",
      "FI",
      "FR",
      "GB",
      "GR",
      "HK",
      "HR",
      "HU",
      "ID",
      "IE",
      "IL",
      "IT",
      "KW",
      "LT",
      "LU",
      "LV",
      "MT",
      "MX",
      "NL",
      "NZ",
      "PH",
      "PL",
      "PT",
      "PY",
      "RO",
      "SA",
      "SE",
      "SG",
      "SI",
      "SK",
      "US"
    ],
    "discount": "5 $",
    "types": [
      {
        "id": 2,
        "name": "Order discount"
      }
    ],
    "image": "http://cdn.admitad.com/campaign/images/2025/9/5/20543-75ebe1c2bc996c2b.svg",
    "species": "action",
    "categories": [
      {
        "id": 8,
        "name": "Computers & Electronics"
      }
    ],
    "name": "$5 off on REDMAGIC 9 Pro with Gamepad 2 Bundle",
    "language": "en",
    "is_unique": false,
    "is_personal": false,
    "is_tracking_promo_code": false,
    "customer_type": null,
    "has_affiliate_link": true,
    "promocode": "NOT REQUIRED",
    "frameset_link": "https://yyczo.com/coupon/iblksg4fjf5af0702a2756637026d8/",
    "goto_link": "https://yyczo.com/g/c2vqx6bcn55af0702a2756637026d8/?i=3"
  },
  {
    "status": "active",
    "rating": "0.00",
    "campaign": {
      "id": 20543,
      "name": "Redmagic WW",
      "site_url": "https://global.redmagic.gg/"
    },
    "description": "",
    "short_name": "40% off on REDMAGIC Gaming Mouse Pad",
    "exclusive": false,
    "date_end": null,
    "date_start": "2024-04-17T00:00:00",
    "id": 748699,
    "regions": [
      "AE",
      "AT",
      "AU",
      "BE",
      "BG",
      "BR",
      "CA",
      "CL",
      "CY",
      "CZ",
      "DE",
      "DK",
      "EE",
      "EG",
      "ES",
      "FI",
      "FR",
      "GB",
      "GR",
      "HK",
      "HR",
      "HU",
      "ID",
      "IE",
      "IL",
      "IT",
      "KW",
      "LT",
      "LU",
      "LV",
      "MT",
      "MX",
      "NL",
      "NZ",
      "PH",
      "PL",
      "PT",
      "PY",
      "RO",
      "SA",
      "SE",
      "SG",
      "SI",
      "SK",
      "US"
    ],
    "discount": "40%",
    "types": [
      {
        "id": 2,
        "name": "Order discount"
      }
    ],
    "image": "http://cdn.admitad.com/campaign/images/2025/9/5/20543-75ebe1c2bc996c2b.svg",
    "species": "action",
    "categories": [
      {
        "id": 8,
        "name": "Computers & Electronics"
      }
    ],
    "name": "40% off on REDMAGIC Gaming Mouse Pad",
    "language": "en",
    "is_unique": false,
    "is_personal": false,
    "is_tracking_promo_code": false,
    "customer_type": null,
    "has_affiliate_link": true,
    "promocode": "NOT REQUIRED",
    "frameset_link": "https://yyczo.com/coupon/laqx5bsyyu5af0702a2756637026d8/",
    "goto_link": "https://yyczo.com/g/xyg7832gqm5af0702a2756637026d8/?i=3"
  },
  {
    "status": "active",
    "rating": "0.00",
    "campaign": {
      "id": 20543,
      "name": "Redmagic WW",
      "site_url": "https://global.redmagic.gg/"
    },
    "description": "",
    "short_name": "30% off on REDMAGIC Gaming Mouse",
    "exclusive": false,
    "date_end": null,
    "date_start": "2024-04-17T00:00:00",
    "id": 748698,
    "regions": [
      "AE",
      "AT",
      "AU",
      "BE",
      "BG",
      "BR",
      "CA",
      "CL",
      "CY",
      "CZ",
      "DE",
      "DK",
      "EE",
      "EG",
      "ES",
      "FI",
      "FR",
      "GB",
      "GR",
      "HK",
      "HR",
      "HU",
      "ID",
      "IE",
      "IL",
      "IT",
      "KW",
      "LT",
      "LU",
      "LV",
      "MT",
      "MX",
      "NL",
      "NZ",
      "PH",
      "PL",
      "PT",
      "PY",
      "RO",
      "SA",
      "SE",
      "SG",
      "SI",
      "SK",
      "US"
    ],
    "discount": "30%",
    "types": [
      {
        "id": 2,
        "name": "Order discount"
      }
    ],
    "image": "http://cdn.admitad.com/campaign/images/2025/9/5/20543-75ebe1c2bc996c2b.svg",
    "species": "action",
    "categories": [
      {
        "id": 8,
        "name": "Computers & Electronics"
      }
    ],
    "name": "30% off on REDMAGIC Gaming Mouse",
    "language": "en",
    "is_unique": false,
    "is_personal": false,
    "is_tracking_promo_code": false,
    "customer_type": null,
    "has_affiliate_link": true,
    "promocode": "NOT REQUIRED",
    "frameset_link": "https://yyczo.com/coupon/e93xaelfjm5af0702a2756637026d8/",
    "goto_link": "https://yyczo.com/g/jkq0oo2s555af0702a2756637026d8/?i=3"
  },
  {
    "status": "active",
    "rating": "0.00",
    "campaign": {
      "id": 20543,
      "name": "Redmagic WW",
      "site_url": "https://global.redmagic.gg/"
    },
    "description": "",
    "short_name": "20% off on REDMAGIC Mechanical Keyboard",
    "exclusive": false,
    "date_end": null,
    "date_start": "2024-04-17T00:00:00",
    "id": 748697,
    "regions": [
      "AE",
      "AT",
      "AU",
      "BE",
      "BG",
      "BR",
      "CA",
      "CL",
      "CY",
      "CZ",
      "DE",
      "DK",
      "EE",
      "EG",
      "ES",
      "FI",
      "FR",
      "GB",
      "GR",
      "HK",
      "HR",
      "HU",
      "ID",
      "IE",
      "IL",
      "IT",
      "KW",
      "LT",
      "LU",
      "LV",
      "MT",
      "MX",
      "NL",
      "NZ",
      "PH",
      "PL",
      "PT",
      "PY",
      "RO",
      "SA",
      "SE",
      "SG",
      "SI",
      "SK",
      "US"
    ],
    "discount": "20%",
    "types": [
      {
        "id": 2,
        "name": "Order discount"
      }
    ],
    "image": "http://cdn.admitad.com/campaign/images/2025/9/5/20543-75ebe1c2bc996c2b.svg",
    "species": "action",
    "categories": [
      {
        "id": 8,
        "name": "Computers & Electronics"
      }
    ],
    "name": "20% off on REDMAGIC Mechanical Keyboard",
    "language": "en",
    "is_unique": false,
    "is_personal": false,
    "is_tracking_promo_code": false,
    "customer_type": null,
    "has_affiliate_link": true,
    "promocode": "NOT REQUIRED",
    "frameset_link": "https://yyczo.com/coupon/rn8m7ky73o5af0702a2756637026d8/",
    "goto_link": "https://yyczo.com/g/xz7s12pzn75af0702a2756637026d8/?i=3"
  },
  {
    "status": "active",
    "rating": "0.01",
    "campaign": {
      "id": 20543,
      "name": "Redmagic WW",
      "site_url": "https://global.redmagic.gg/"
    },
    "description": "Promo Code is not required",
    "short_name": "$10 off code for REDMAGIC 7 series phones",
    "exclusive": false,
    "date_end": null,
    "date_start": "2023-03-28T08:36:06",
    "id": 529983,
    "regions": [
      "AE",
      "AT",
      "AU",
      "BE",
      "BG",
      "BR",
      "CA",
      "CL",
      "CY",
      "CZ",
      "DE",
      "DK",
      "EE",
      "EG",
      "ES",
      "FI",
      "FR",
      "GB",
      "GR",
      "HK",
      "HR",
      "HU",
      "ID",
      "IE",
      "IL",
      "IT",
      "KW",
      "LT",
      "LU",
      "LV",
      "MT",
      "MX",
      "NL",
      "NZ",
      "PH",
      "PL",
      "PT",
      "PY",
      "RO",
      "SA",
      "SE",
      "SG",
      "SI",
      "SK",
      "US"
    ],
    "discount": "10 $",
    "types": [
      {
        "id": 2,
        "name": "Order discount"
      }
    ],
    "image": "http://cdn.admitad.com/campaign/images/2025/9/5/20543-75ebe1c2bc996c2b.svg",
    "species": "promocode",
    "categories": [
      {
        "id": 8,
        "name": "Computers & Electronics"
      },
      {
        "id": 19,
        "name": "Games"
      }
    ],
    "name": "$10 off code for REDMAGIC 7 series phones",
    "language": "en",
    "is_unique": false,
    "is_personal": false,
    "is_tracking_promo_code": false,
    "customer_type": null,
    "has_affiliate_link": true,
    "promocode": "AFFRM710",
    "frameset_link": "https://yyczo.com/coupon/asztbj4w9d5af0702a2756637026d8/",
    "goto_link": "https://yyczo.com/g/5ech344ldx5af0702a2756637026d8/?i=3"
  }
]