[
  {
    "id": 13903,
    "name": "Tickets [CPS] UA",
    "image": "https://cdn.admitad-connect.com/campaign/images/2023/3/29/13903-b220728043a7dbfd.svg",
    "img": "platform/13903.svg",
    "categories": [
      {
        "name": "Tours",
        "id": 234,
        "language": "en",
        "parent": {
          "name": "Travel & Tourism",
          "id": 40,
          "language": "en",
          "parent": null
        }
      },
      {
        "name": "Buses",
        "id": 207,
        "language": "en",
        "parent": {
          "name": "Travel & Tourism",
          "id": 40,
          "language": "en",
          "parent": null
        }
      },
      {
        "name": "Carsharing",
        "id": 210,
        "language": "en",
        "parent": {
          "name": "Travel & Tourism",
          "id": 40,
          "language": "en",
          "parent": null
        }
      },
      {
        "name": "Metasearch Engines",
        "id": 218,
        "language": "en",
        "parent": {
          "name": "Travel & Tourism",
          "id": 40,
          "language": "en",
          "parent": null
        }
      },
      {
        "name": "Hotels",
        "id": 41,
        "language": "en",
        "parent": {
          "name": "Travel & Tourism",
          "id": 40,
          "language": "en",
          "parent": null
        }
      },
      {
        "name": "Package Holidays",
        "id": 45,
        "language": "en",
        "parent": {
          "name": "Travel & Tourism",
          "id": 40,
          "language": "en",
          "parent": null
        }
      },
      {
        "name": "Ridesharing & Taxi",
        "id": 209,
        "language": "en",
        "parent": {
          "name": "Travel & Tourism",
          "id": 40,
          "language": "en",
          "parent": null
        }
      },
      {
        "name": "Vacation Rentals",
        "id": 212,
        "language": "en",
        "parent": {
          "name": "Travel & Tourism",
          "id": 40,
          "language": "en",
          "parent": null
        }
      },
      {
        "name": "Travel & Tourism",
        "id": 40,
        "language": "en",
        "parent": null
      },
      {
        "name": "Flights",
        "id": 44,
        "language": "en",
        "parent": {
          "name": "Travel & Tourism",
          "id": 40,
          "language": "en",
          "parent": null
        }
      },
      {
        "name": "Trains",
        "id": 208,
        "language": "en",
        "parent": {
          "name": "Travel & Tourism",
          "id": 40,
          "language": "en",
          "parent": null
        }
      },
      {
        "name": "Cruises",
        "id": 211,
        "language": "en",
        "parent": {
          "name": "Travel & Tourism",
          "id": 40,
          "language": "en",
          "parent": null
        }
      },
      {
        "name": "Car Rentals",
        "id": 91,
        "language": "en",
        "parent": {
          "name": "Travel & Tourism",
          "id": 40,
          "language": "en",
          "parent": null
        }
      },
      {
        "name": "Smart Tracking_UA",
        "id": 379,
        "language": "en",
        "parent": null
      }
    ],
    "category": {
      "name": "Tours",
      "id": 234,
      "language": "en",
      "parent": {
        "name": "Travel & Tourism",
        "id": 40,
        "language": "en",
        "parent": null
      }
    }
  },
  {
    "id": 42148,
    "name": "Travelking PL & HU",
    "image": "https://cdn.admitad-connect.com/campaign/images/2023/11/1/42148-acc3e8710ac31851.svg",
    "img": "platform/42148.svg",
    "categories": [
      {
        "name": "Travel & Tourism",
        "id": 40,
        "language": "en",
        "parent": null
      },
      {
        "name": "Tours",
        "id": 234,
        "language": "en",
        "parent": {
          "name": "Travel & Tourism",
          "id": 40,
          "language": "en",
          "parent": null
        }
      },
      {
        "name": "Package Holidays",
        "id": 45,
        "language": "en",
        "parent": {
          "name": "Travel & Tourism",
          "id": 40,
          "language": "en",
          "parent": null
        }
      },
      {
        "name": "Hotels",
        "id": 41,
        "language": "en",
        "parent": {
          "name": "Travel & Tourism",
          "id": 40,
          "language": "en",
          "parent": null
        }
      }
    ],
    "category": {
      "name": "Tours",
      "id": 234,
      "language": "en",
      "parent": {
        "name": "Travel & Tourism",
        "id": 40,
        "language": "en",
        "parent": null
      }
    }
  }
]